Workbook

Sheet 说明
A1: 赛可心理测试（psyctest.cn）测评主题综合分析
A3: 分析对象：站点全部 1799 个测评（标题+完整简介），来源 https://m.psyctest.cn/tests/，抓取时间 2026-10-01
A4: 主题数量：390 个测评主题，归入 14 个一级主题域
A5: 字段说明：
A6: · 一级主题域：按心理测评场景归纳的十四大类
A7: · 测评主题：该域下有实际测评支撑的具体主题
A8: · 主题说明：该主题的内涵与测评视角
A9: · 关联测评数：按主题关键词在测评标题/简介中匹配得到的数量（同一测评可关联多个主题，故各主题计数之和不等于测评总数）
A10: · 代表测评示例：该主题下最多 3 个测评标题（优先取标题命中者）

Sheet 测评主题
A1: 序号 | B1: 一级主题域 | C1: 测评主题 | D1: 主题说明 | E1: 关联测评数 | F1: 代表测评示例（最多3个）
A2: 1 | B2: 人格与个性 | C2: MBTI 16型人格 | D2: 基于MBTI理论框架的16型人格测评，含28/72/93/145/200题等多版本，是站点最核心的旗舰测评主题。 | E2: 33 | F2: 【超准】I人 or E人测试：你属于哪一种MBTI人格类型？；MBTI人格：S型 or N型细分维度测试；测测你的MBTI电竞人格是什么？
A3: 2 | B3: 人格与个性 | C3: MBTI维度细分（I/E、S/N、T/F、J/P） | D3: 针对MBTI单一维度的深入测评，如I人/E人、S型/N型细分、电竞人格等衍生玩法。 | E3: 5 | F3: 【超准】I人 or E人测试：你属于哪一种MBTI人格类型？；MBTI人格：S型 or N型细分维度测试；测测你的MBTI电竞人格是什么？
A4: 3 | B4: 人格与个性 | C4: 大五人格（Big Five） | D4: 以开放性、尽责性、外向性、宜人性、神经质五维度刻画人格，含BFI-44、NEO-PI-R、TIPI、CBF-PI等标准量表。 | E4: 10 | F4: 大五人格测试240题完整版：NEO-PI-R BigFive人格量表「永久免费，无需注册」；中国大五人格问卷极简版（CBF-PI-15）在线测试：快速洞察你的五大人格特质；OCEAN BigFive 大五人格测试（TIPI量表）10题简版快速测评
A5: 4 | B5: 人格与个性 | C5: 九型人格 | D5: 将人格分为完美型、助人型、成就型等九种类型的人格测评，含36/90/144题多版本。 | E5: 4 | F5: 九型人格免费在线测试|144题专业版；九型人格属性倾向免费在线测试|90题经典版；九型人格免费在线测试|36题精简版
A6: 5 | B6: 人格与个性 | C6: 艾森克人格EPQ | D6: 艾森克人格问卷，从内外向、神经质、精神质、掩饰性四维度评估人格。 | E6: 3 | F6: 艾森克人格问卷EPQ免费在线测试|88题完整版；艾森克EPQ人格测试量表在线测试|85题入职性格测试版；艾森克情绪稳定性（EES）免费在线测试
A7: 6 | B7: 人格与个性 | C7: 卡特尔16PF人格因素 | D7: 卡特尔16项人格因素问卷，经典特质论量表。 | E7: 1 | F7: 卡特尔16PF人格特质量表免费在线测试
A8: 7 | B8: 人格与个性 | C8: DISC行为风格 | D8: 从支配、影响、稳健、谨慎四型分析行为风格的职场经典测评。 | E8: 3 | F8: DISC职业性格测试|免费；SM倾向测试：M接受程度自评量表（Masochism Receptivity Inventory，MRI）；BDSM性偏好倾向免费在线测试：测测你的字母圈人格属性
A9: 8 | B9: 人格与个性 | C9: PDP性格类型 | D9: PDP专业性格诊断（老虎、孔雀、考拉、猫头鹰等动物型）。 | E9: 2 | F9: PDP性格测试（快捷版）；PDP职业性格测试
A10: 9 | B10: 人格与个性 | C10: FPA性格色彩 | D10: 红蓝黄绿四色性格分析体系。 | E10: 4 | F10: 爱情性格色彩测试：六型恋爱人格测评，测出你的恋爱风格与专属颜色；心理测试：隐藏在你内心深处的性格色彩是什么？；FPA性格色彩免费测试
A11: 10 | B11: 人格与个性 | C11: 四种气质类型 | D11: 胆汁质、多血质、粘液质、抑郁质的经典气质学说测评。 | E11: 2 | F11: 四气质类型免费在线测试；职场气质测试：测你职场上自带哪种气质
A12: 11 | B12: 人格与个性 | C12: 菲尔人格测试 | D12: 菲尔博士经典人格测验，10题快速画像。 | E12: 1 | F12: 菲尔人格测试|免费
A13: 12 | B13: 人格与个性 | C13: 内向-外向倾向 | D13: 评估能量指向偏内向还是外向的性格倾向测评。 | E13: 45 | F13: 性格测试：你内向还是外向还是双向型性格？；性格测试：你是内向型还是外向型？一测便知！；你是内向还是外向？快速测出你的性格类型！
... A392: 391 | B392: 投射与潜意识 | C392: 日常物品选择投射 | D392: 电梯、座位、寝具、房间布置等日常选择读心。 | E392: 24 | F392: 车厢座位性格测试；趣味测试：从搭电梯看你工作升迁运；等车姿势测试你的职场位置

Sheet 统计
A1: 一级主题域统计
A2: 一级主题域 | B2: 主题数 | C2: 关联测评数合计
A3: 人格与个性 | B3: =COUNTIF(测评主题!B:B,A3) | C3: =SUMIF(测评主题!B:B,A3,测评主题!E:E)
A4: 恋爱与亲密关系 | B4: =COUNTIF(测评主题!B:B,A4) | C4: =SUMIF(测评主题!B:B,A4,测评主题!E:E)
A5: 婚姻与家庭 | B5: =COUNTIF(测评主题!B:B,A5) | C5: =SUMIF(测评主题!B:B,A5,测评主题!E:E)
A6: 人际与社交 | B6: =COUNTIF(测评主题!B:B,A6) | C6: =SUMIF(测评主题!B:B,A6,测评主题!E:E)
A7: 职场与事业 | B7: =COUNTIF(测评主题!B:B,A7) | C7: =SUMIF(测评主题!B:B,A7,测评主题!E:E)
A8: 心理健康 | B8: =COUNTIF(测评主题!B:B,A8) | C8: =SUMIF(测评主题!B:B,A8,测评主题!E:E)
A9: 情绪与压力管理 | B9: =COUNTIF(测评主题!B:B,A9) | C9: =SUMIF(测评主题!B:B,A9,测评主题!E:E)
A10: 认知与能力 | B10: =COUNTIF(测评主题!B:B,A10) | C10: =SUMIF(测评主题!B:B,A10,测评主题!E:E)
A11: 自我成长与人生观 | B11: =COUNTIF(测评主题!B:B,A11) | C11: =SUMIF(测评主题!B:B,A11,测评主题!E:E)
A12: 金钱与财富 | B12: =COUNTIF(测评主题!B:B,A12) | C12: =SUMIF(测评主题!B:B,A12,测评主题!E:E)
A13: 性与性别心理 | B13: =COUNTIF(测评主题!B:B,A13) | C13: =SUMIF(测评主题!B:B,A13,测评主题!E:E)
A14: 亲子儿童与青少年 | B14: =COUNTIF(测评主题!B:B,A14) | C14: =SUMIF(测评主题!B:B,A14,测评主题!E:E)
... A16: 投射与潜意识 | B16: =COUNTIF(测评主题!B:B,A16) | C16: =SUMIF(测评主题!B:B,A16,测评主题!E:E)
A17: 合计 | B17: =SUM(B3:B16) | C17: =SUM(C3:C16)
