Workbook

Sheet 说明
A1: 赛可心理测试测评主题 · 测评题目与维度设计总表
A3: 覆盖范围：391 个测评主题（与《psyctest_测评主题.xlsx》序号一致），共 10,275 道原创题目
A4: 生成时间：2026-10-01；题目为本项目原创设计，未抄录任何真实量表原文
A6: 工作表结构：
A7: ① 主题总览：每个主题一行（题数、维度数由公式统计）
A8: ② 题目明细：每道题一行，含题干、题型、所属维度、各选项文本与分值
A9: ③ 维度设置：每个维度一行，含说明、包含题号、最低分/总分（公式汇总）
A10: ④ 分数段分析：每个维度 3-5 个分数段，含评级、分析解读与建议
A12: 计分口径：
A13: · 单选题：得分为所选选项的分值。情景/趣味类单选 4-5 个选项分值为 1..n 的排列；
A14: · 频率自评类单选：选项固定 从不/偶尔/经常/总是（1-4 分），反向陈述题分值 4/3/2/1；
A15: · 多选题（题干注明）：得分为所选选项分值之和（0/1/2 分制，选得越多分越高）；
... A23: 如需用于筛查场景，建议由专业人士复核分数段解读后再上线。

Sheet 主题总览
A1: 主题序号 | B1: 一级主题域 | C1: 测评主题 | D1: 出题风格 | E1: 题数 | F1: 维度数 | G1: 分数段数
A2: 1 | B2: 人格与个性 | C2: MBTI 16型人格 | D2: 情景选择 | E2: =COUNTIF(题目明细!$A:$A,A2) | F2: =COUNTIF(维度设置!$A:$A,A2) | G2: =COUNTIF(分数段分析!$A:$A,A2)
A3: 2 | B3: 人格与个性 | C3: MBTI维度细分（I/E、S/N、T/F、J/P） | D3: 情景选择 | E3: =COUNTIF(题目明细!$A:$A,A3) | F3: =COUNTIF(维度设置!$A:$A,A3) | G3: =COUNTIF(分数段分析!$A:$A,A3)
A4: 3 | B4: 人格与个性 | C4: 大五人格（Big Five） | D4: 情景选择 | E4: =COUNTIF(题目明细!$A:$A,A4) | F4: =COUNTIF(维度设置!$A:$A,A4) | G4: =COUNTIF(分数段分析!$A:$A,A4)
A5: 4 | B5: 人格与个性 | C5: 九型人格 | D5: 情景选择 | E5: =COUNTIF(题目明细!$A:$A,A5) | F5: =COUNTIF(维度设置!$A:$A,A5) | G5: =COUNTIF(分数段分析!$A:$A,A5)
A6: 5 | B6: 人格与个性 | C6: 艾森克人格EPQ | D6: 情景选择 | E6: =COUNTIF(题目明细!$A:$A,A6) | F6: =COUNTIF(维度设置!$A:$A,A6) | G6: =COUNTIF(分数段分析!$A:$A,A6)
A7: 6 | B7: 人格与个性 | C7: 卡特尔16PF人格因素 | D7: 情景选择 | E7: =COUNTIF(题目明细!$A:$A,A7) | F7: =COUNTIF(维度设置!$A:$A,A7) | G7: =COUNTIF(分数段分析!$A:$A,A7)
A8: 7 | B8: 人格与个性 | C8: DISC行为风格 | D8: 情景选择 | E8: =COUNTIF(题目明细!$A:$A,A8) | F8: =COUNTIF(维度设置!$A:$A,A8) | G8: =COUNTIF(分数段分析!$A:$A,A8)
A9: 8 | B9: 人格与个性 | C9: PDP性格类型 | D9: 情景选择 | E9: =COUNTIF(题目明细!$A:$A,A9) | F9: =COUNTIF(维度设置!$A:$A,A9) | G9: =COUNTIF(分数段分析!$A:$A,A9)
A10: 9 | B10: 人格与个性 | C10: FPA性格色彩 | D10: 情景选择 | E10: =COUNTIF(题目明细!$A:$A,A10) | F10: =COUNTIF(维度设置!$A:$A,A10) | G10: =COUNTIF(分数段分析!$A:$A,A10)
A11: 10 | B11: 人格与个性 | C11: 四种气质类型 | D11: 情景选择 | E11: =COUNTIF(题目明细!$A:$A,A11) | F11: =COUNTIF(维度设置!$A:$A,A11) | G11: =COUNTIF(分数段分析!$A:$A,A11)
A12: 11 | B12: 人格与个性 | C12: 菲尔人格测试 | D12: 情景选择 | E12: =COUNTIF(题目明细!$A:$A,A12) | F12: =COUNTIF(维度设置!$A:$A,A12) | G12: =COUNTIF(分数段分析!$A:$A,A12)
A13: 12 | B13: 人格与个性 | C13: 内向-外向倾向 | D13: 情景选择 | E13: =COUNTIF(题目明细!$A:$A,A13) | F13: =COUNTIF(维度设置!$A:$A,A13) | G13: =COUNTIF(分数段分析!$A:$A,A13)
... A392: 391 | B392: 投射与潜意识 | C392: 日常物品选择投射 | D392: 轻松趣味 | E392: =COUNTIF(题目明细!$A:$A,A392) | F392: =COUNTIF(维度设置!$A:$A,A392) | G392: =COUNTIF(分数段分析!$A:$A,A392)

Sheet 题目明细
A1: 主题序号 | B1: 一级主题域 | C1: 测评主题 | D1: 题号 | E1: 题干 | F1: 题型 | G1: 维度代码 | H1: 维度名称 | I1: 选项A文本 | J1: A分值 | K1: 选项B文本 | L1: B分值 | M1: 选项C文本 | N1: C分值 | O1: 选项D文本 | P1: D分值 | Q1: 选项E文本 | R1: E分值 | S1: 题目满分 | T1: 题目最低分
A2: 1 | B2: 人格与个性 | C2: MBTI 16型人格 | D2: 1 | E2: 周五晚上朋友临时约聚会，你刚到家很累，你会… | F2: 单选 | G2: D1 | H2: 能量取向 | I2: 兴奋答应还叫上朋友 | J2: 4 | K2: 推掉聚会在家安静休息 | L2: 1 | M2: 看熟人多不多再决定 | N2: 2 | O2: 先去一小时再提前撤 | P2: 3 | S2: =MAX(J2,L2,N2,P2) | T2: =MIN(J2,L2,N2,P2)
A3: 1 | B3: 人格与个性 | C3: MBTI 16型人格 | D3: 2 | E3: 到陌生城市出差，晚上有空闲，你多半… | F3: 单选 | G3: D1 | H3: 能量取向 | I3: 在酒店复盘一天的工作 | J3: 1 | K3: 去附近夜市走一走 | L3: 3 | M3: 点份外卖边吃边看剧 | N3: 2 | O3: 约当地人出来聊聊天 | P3: 4 | S3: =MAX(J3,L3,N3,P3) | T3: =MIN(J3,L3,N3,P3)
A4: 1 | B4: 人格与个性 | C4: MBTI 16型人格 | D4: 3 | E4: 连续几天独自在家办公后，你的状态通常是… | F4: 单选 | G4: D1 | H4: 能量取向 | I4: 正常，偶尔聊聊天 | J4: 2 | K4: 有点闷，想找人说话 | L4: 3 | M4: 越独处越有精神头 | N4: 1 | O4: 憋坏了，立刻约人 | P4: 4 | S4: =MAX(J4,L4,N4,P4) | T4: =MIN(J4,L4,N4,P4)
A5: 1 | B5: 人格与个性 | C5: MBTI 16型人格 | D5: 4 | E5: 团队破冰要求轮流发言，你的内心是… | F5: 单选 | G5: D1 | H5: 能量取向 | I5: 轮到就说并不紧张 | J5: 3 | K5: 盼着快点轮完坐下 | L5: 1 | M5: 提前打好简短腹稿 | N5: 2 | O5: 跃跃欲试想讲得有趣 | P5: 4 | S5: =MAX(J5,L5,N5,P5) | T5: =MIN(J5,L5,N5,P5)
A6: 1 | B6: 人格与个性 | C6: MBTI 16型人格 | D6: 5 | E6: 手机安静一整天没人找你，你会… | F6: 单选 | G6: D1 | H6: 能量取向 | I6: 翻翻群消息有点空落 | J6: 3 | K6: 主动发消息找人聊天 | L6: 4 | M6: 该干嘛干嘛不受影响 | N6: 2 | O6: 觉得清净正好专注 | P6: 1 | S6: =MAX(J6,L6,N6,P6) | T6: =MIN(J6,L6,N6,P6)
A7: 1 | B7: 人格与个性 | C7: MBTI 16型人格 | D7: 6 | E7: 婚宴上被安排到陌生同桌，一顿饭时间你会… | F7: 单选 | G7: D1 | H7: 能量取向 | I7: 带动全桌互相认识 | J7: 4 | K7: 聊得投机交换联系方式 | L7: 3 | M7: 和邻座简短寒暄几句 | N7: 2 | O7: 安静吃饭礼貌回应 | P7: 1 | S7: =MAX(J7,L7,N7,P7) | T7: =MIN(J7,L7,N7,P7)
A8: 1 | B8: 人格与个性 | C8: MBTI 16型人格 | D8: 7 | E8: 遇到烦心事或压力大的时候，你更愿意… | F8: 单选 | G8: D1 | H8: 能量取向 | I8: 关起门来独自消化 | J8: 2 | K8: 写下来自己慢慢梳理 | L8: 1 | M8: 见到熟人就想倾诉 | N8: 4 | O8: 找一两个信任的人说 | P8: 3 | S8: =MAX(J8,L8,N8,P8) | T8: =MIN(J8,L8,N8,P8)
A9: 1 | B9: 人格与个性 | C9: MBTI 16型人格 | D9: 8 | E9: 想弄清一份体检报告的细节，你会… | F9: 单选 | G9: D1 | H9: 能量取向 | I9: 拉懂医的朋友一起看 | J9: 3 | K9: 记下来下次问医生 | L9: 2 | M9: 上网逐条查资料 | N9: 1 | O9: 发到群里集思广益 | P9: 4 | S9: =MAX(J9,L9,N9,P9) | T9: =MIN(J9,L9,N9,P9)
A10: 1 | B10: 人格与个性 | C10: MBTI 16型人格 | D10: 9 | E10: 周末大扫除时，你更享受… | F10: 单选 | G10: D1 | H10: 能量取向 | I10: 家人各自分工不打扰 | J10: 2 | K10: 一个人边听歌边干活 | L10: 1 | M10: 边干活边和家人闲聊 | N10: 3 | O10: 叫上朋友一起动手 | P10: 4 | S10: =MAX(J10,L10,N10,P10) | T10: =MIN(J10,L10,N10,P10)
A11: 1 | B11: 人格与个性 | C11: MBTI 16型人格 | D11: 10 | E11: 参加一场陌生的行业酒会，你通常… | F11: 单选 | G11: D1 | H11: 能量取向 | I11: 换几个人各聊上几句 | J11: 3 | K11: 和陌生人聊得火热 | L11: 4 | M11: 只和认识的人待一起 | N11: 2 | O11: 找角落待够时间就走 | P11: 1 | S11: =MAX(J11,L11,N11,P11) | T11: =MIN(J11,L11,N11,P11)
A12: 1 | B12: 人格与个性 | C12: MBTI 16型人格 | D12: 11 | E12: 学习一项新技能，你更偏爱… | F12: 单选 | G12: D1 | H12: 能量取向 | I12: 看录播慢慢消化 | J12: 2 | K12: 直接报班融入班级 | L12: 4 | M12: 找学习搭子互相打卡 | N12: 3 | O12: 看教程自己反复练 | P12: 1 | S12: =MAX(J12,L12,N12,P12) | T12: =MIN(J12,L12,N12,P12)
A13: 1 | B13: 人格与个性 | C13: MBTI 16型人格 | D13: 12 | E13: 旅行时遇到健谈的当地人，你的反应是… | F13: 单选 | G13: D1 | H13: 能量取向 | I13: 简单应答两句道别 | J13: 2 | K13: 一聊半小时互加好友 | L13: 4 | M13: 顺着聊起风土人情 | N13: 3 | O13: 礼貌点头继续赶路 | P13: 1 | S13: =MAX(J13,L13,N13,P13) | T13: =MIN(J13,L13,N13,P13)
... A2987: 100 | B2987: 婚姻与家庭 | C2987: 离婚倾向与动机 | D2987: 7 | E2987: 当你生病或情绪低落时，伴侣的表现通常是： | F2987: 单选 | G2987: D1 | H2987: 婚姻满意度 | I2987: 会关心但方式笨拙 | J2987: 3 | K2987: 细心照顾耐心陪伴 | L2987: 4 | M2987: 问一句就忙自己的 | N2987: 2 | O2987: 察觉不到我的状态 | P2987: 1 | S2987: =MAX(J2987,L2987,N2987,P2987) | T2987: =MIN(J2987,L2987,N2987,P2987)
A2988: 100 | B2988: 婚姻与家庭 | C2988: 离婚倾向与动机 | D2988: 8 | E2988: 以下哪些描述更贴近你目前的婚姻状态（多选）： | F2988: 多选 | G2988: D1 | H2988: 婚姻满意度 | I2988: 保留专属的小默契 | J2988: 2 | K2988: 偶有心动瞬间闪回 | L2988: 1 | M2988: 相处像合租的室友 | N2988: 0 | O2988: 想起对方先想到烦 | P2988: 0 | Q2988: 仍愿意为关系花心思 | R2988: 2 | S2988: =MAX(J2988,L2988,N2988,P2988,R2988) | T2988: =MIN(J2988,L2988,N2988,P2988,R2988)
A2989: 100 | B2989: 婚姻与家庭 | C2989: 离婚倾向与动机 | D2989: 9 | E2989: 激烈争吵到最凶的时候，你一般会怎么做： | F2989: 单选 | G2989: D2 | H2989: 冲突修复能力 | I2989: 喊暂停冷静再谈 | J2989: 4 | K2989: 翻旧账往痛处说 | L2989: 1 | M2989: 闭嘴忍着不吭声 | N2989: 3 | O2989: 摔门离开不回头 | P2989: 2 | S2989: =MAX(J2989,L2989,N2989,P2989) | T2989: =MIN(J2989,L2989,N2989,P2989)
A2990: 100 | B2990: 婚姻与家庭 | C2990: 离婚倾向与动机 | D2990: 10 | E2990: 吵完架的当天晚上，通常是谁先缓和气氛： | F2990: 单选 | G2990: D2 | H2990: 冲突修复能力 | I2990: 总得有人递台阶 | J2990: 2 | K2990: 我们很快互相搭话 | L2990: 4 | M2990: 先低头的人是我 | N2990: 3 | O2990: 常常僵持好几天 | P2990: 1 | S2990: =MAX(J2990,L2990,N2990,P2990) | T2990: =MIN(J2990,L2990,N2990,P2990)
A2991: 100 | B2991: 婚姻与家庭 | C2991: 离婚倾向与动机 | D2991: 11 | E2991: 对同一件事反复起冲突时，你们会： | F2991: 单选 | G2991: D2 | H2991: 冲突修复能力 | I2991: 只提醒不深谈 | J2991: 3 | K2991: 等对方先改变 | L2991: 2 | M2991: 试着找折中方案 | N2991: 4 | O2991: 吵完就过下次再吵 | P2991: 1 | S2991: =MAX(J2991,L2991,N2991,P2991) | T2991: =MIN(J2991,L2991,N2991,P2991)
A2992: 100 | B2992: 婚姻与家庭 | C2992: 离婚倾向与动机 | D2992: 12 | E2992: 冷静之后复盘吵架原因，你的习惯是： | F2992: 单选 | G2992: D2 | H2992: 冲突修复能力 | I2992: 从不想那些糟心事 | J2992: 1 | K2992: 想想就算了不说出 | L2992: 2 | M2992: 找机会把感受说开 | N2992: 4 | O2992: 跟朋友吐槽取建议 | P2992: 3 | S2992: =MAX(J2992,L2992,N2992,P2992) | T2992: =MIN(J2992,L2992,N2992,P2992)
A2993: 100 | B2993: 婚姻与家庭 | C2993: 离婚倾向与动机 | D2993: 13 | E2993: 对方主动道歉或示好时，你的第一反应通常是： | F2993: 单选 | G2993: D2 | H2993: 冲突修复能力 | I2993: 接受但仍有点别扭 | J2993: 3 | K2993: 继续冷着脸不理 | L2993: 1 | M2993: 顺势接住握手言和 | N2993: 4 | O2993: 嘴上说没事心里堵 | P2993: 2 | S2993: =MAX(J2993,L2993,N2993,P2993) | T2993: =MIN(J2993,L2993,N2993,P2993)
A2994: 100 | B2994: 婚姻与家庭 | C2994: 离婚倾向与动机 | D2994: 14 | E2994: 面对暂时解不开的分歧，你的态度是： | F2994: 单选 | G2994: D2 | H2994: 冲突修复能力 | I2994: 认定无法调和了 | J2994: 1 | K2994: 必须马上争出对错 | L2994: 2 | M2994: 允许先放放再谈 | N2994: 4 | O2994: 各自保留互不干涉 | P2994: 3 | S2994: =MAX(J2994,L2994,N2994,P2994) | T2994: =MIN(J2994,L2994,N2994,P2994)
A2995: 100 | B2995: 婚姻与家庭 | C2995: 离婚倾向与动机 | D2995: 15 | E2995: 当你意识到自己也有错时，通常会： | F2995: 单选 | G2995: D2 | H2995: 冲突修复能力 | I2995: 找机会坦诚认错 | J2995: 4 | K2995: 用行动悄悄弥补 | L2995: 3 | M2995: 绝不肯先低头 | N2995: 1 | O2995: 心里认嘴上不认 | P2995: 2 | S2995: =MAX(J2995,L2995,N2995,P2995) | T2995: =MIN(J2995,L2995,N2995,P2995)
A2996: 100 | B2996: 婚姻与家庭 | C2996: 离婚倾向与动机 | D2996: 16 | E2996: 外部压力大的时候（工作不顺等），你们的相处会： | F2996: 单选 | G2996: D2 | H2996: 冲突修复能力 | I2996: 互相体谅共渡难关 | J2996: 4 | K2996: 容易把火撒给对方 | L2996: 1 | M2996: 话变少但不出恶语 | N2996: 3 | O2996: 频繁冷战互相指责 | P2996: 2 | S2996: =MAX(J2996,L2996,N2996,P2996) | T2996: =MIN(J2996,L2996,N2996,P2996)
A2997: 100 | B2997: 婚姻与家庭 | C2997: 离婚倾向与动机 | D2997: 17 | E2997: 深夜独处时，离婚这个念头在你脑中： | F2997: 单选 | G2997: D3 | H2997: 分离念头与动机 | I2997: 很少出现闪过就过 | J2997: 4 | K2997: 反复盘算具体细节 | L2997: 1 | M2997: 偶尔想起让人烦躁 | N2997: 2 | O2997: 烦心事多时才冒出 | P2997: 3 | S2997: =MAX(J2997,L2997,N2997,P2997) | T2997: =MIN(J2997,L2997,N2997,P2997)
A2998: 100 | B2998: 婚姻与家庭 | C2998: 离婚倾向与动机 | D2998: 18 | E2998: 你考虑过离婚的主要原因是： | F2998: 单选 | G2998: D3 | H2998: 分离念头与动机 | I2998: 没认真想过这事 | J2998: 4 | K2998: 一气之下的冲动 | L2998: 3 | M2998: 长期的失望和委屈 | N2998: 1 | O2998: 性格不合沟通困难 | P2998: 2 | S2998: =MAX(J2998,L2998,N2998,P2998) | T2998: =MIN(J2998,L2998,N2998,P2998)
A2999: 100 | B2999: 婚姻与家庭 | C2999: 离婚倾向与动机 | D2999: 19 | E2999: 如果让你列举必须离婚的硬理由，你能列： | F2999: 单选 | G2999: D3 | H2999: 分离念头与动机 | I2999: 一长串难以辩驳 | J2999: 1 | K2999: 只有情绪上来时能列 | L2999: 2 | M2999: 其实一条也说不清 | N2999: 4 | O2999: 两三条都不算硬 | P2999: 3 | S2999: =MAX(J2999,L2999,N2999,P2999) | T2999: =MIN(J2999,L2999,N2999,P2999)
A3000: 100 | B3000: 婚姻与家庭 | C3000: 离婚倾向与动机 | D3000: 20 | E3000: 身边人劝和或劝分时，你内心的真实倾向： | F3000: 单选 | G3000: D3 | H3000: 分离念头与动机 | I3000: 听完会再想想再定 | J3000: 3 | K3000: 只信自己的判断 | L3000: 4 | M3000: 希望有人替我决定 | N3000: 1 | O3000: 谁的话都容易动摇 | P3000: 2 | S3000: =MAX(J3000,L3000,N3000,P3000) | T3000: =MIN(J3000,L3000,N3000,P3000)
... A3002: 100 | B3002: 婚姻与家庭 | C3002: 离婚倾向与动机 | D3002: 22 | E3002: 当你想象未来五年的生活画面时，画面里： | F3002: 单选 | G3002: D3 | H3002: 分离念头与动机 | I3002: 有家但气氛冷清 | J3002: 3 | K3002: 很模糊不敢细想 | L3002: 2 | M3002: 只有我一个人 | N3002: 1 | O3002: 有伴侣也有共同目标 | P3002: 4 | S3002: =MAX(J3002,L3002,N3002,P3002) | T3002: =MIN(J3002,L3002,N3002,P3002)
A3003: 100 | B3003: 婚姻与家庭 | C3003: 离婚倾向与动机 | D3003: 23 | E3003: 以下哪些情况最近半年你经历过（多选）： | F3003: 多选 | G3003: D3 | H3003: 分离念头与动机 | I3003: 冷战超过一个星期 | J3003: 0 | K3003: 为对方做过暖心小事 | L3003: 2 | M3003: 认真查过离婚手续 | N3003: 0 | O3003: 向人吐槽过想离婚 | P3003: 0 | Q3003: 和伴侣有过开心出游 | R3003: 2 | S3003: =MAX(J3003,L3003,N3003,P3003,R3003) | T3003: =MIN(J3003,L3003,N3003,P3003,R3003)
A3004: 100 | B3004: 婚姻与家庭 | C3004: 离婚倾向与动机 | D3004: 24 | E3004: 如果现在有一档修复婚姻的机会（如咨询），你会： | F3004: 单选 | G3004: D3 | H3004: 分离念头与动机 | I3004: 愿意拉上对方试试 | J3004: 4 | K3004: 先观望对方的态度 | L3004: 2 | M3004: 觉得没用直接拒绝 | N3004: 1 | O3004: 自己先了解着看 | P3004: 3 | S3004: =MAX(J3004,L3004,N3004,P3004) | T3004: =MIN(J3004,L3004,N3004,P3004)
A3005: 101 | B3005: 婚姻与家庭 | C3005: 婚姻第三者风险 | D3005: 1 | E3005: 最近半年，你和伴侣深聊心事和感受的频率是： | F3005: 单选 | G3005: D1 | H3005: 情感投入度 | I3005: 几乎每周都有 | J3005: 4 | K3005: 一个月一两次 | L3005: 3 | M3005: 想不起来何时聊过 | N3005: 1 | O3005: 只在有事时才交谈 | P3005: 2 | S3005: =MAX(J3005,L3005,N3005,P3005) | T3005: =MIN(J3005,L3005,N3005,P3005)
A3006: 101 | B3006: 婚姻与家庭 | C3006: 婚姻第三者风险 | D3006: 2 | E3006: 遇到开心的事，你的第一反应是告诉谁： | F3006: 单选 | G3006: D1 | H3006: 情感投入度 | I3006: 伴侣永远排在首位 | J3006: 4 | K3006: 发到群里谁回算谁 | L3006: 2 | M3006: 看场合在伴侣朋友间切换 | N3006: 3 | O3006: 某位异性朋友更懂我 | P3006: 1 | S3006: =MAX(J3006,L3006,N3006,P3006) | T3006: =MIN(J3006,L3006,N3006,P3006)
A3007: 101 | B3007: 婚姻与家庭 | C3007: 婚姻第三者风险 | D3007: 3 | E3007: 你们上一次专门的二人约会或旅行是什么时候： | F3007: 单选 | G3007: D1 | H3007: 情感投入度 | I3007: 近两个月就有安排 | J3007: 4 | K3007: 一年以上或从没有 | L3007: 1 | M3007: 约过但总被搁置 | N3007: 2 | O3007: 半年之内有过 | P3007: 3 | S3007: =MAX(J3007,L3007,N3007,P3007) | T3007: =MIN(J3007,L3007,N3007,P3007)
A3008: 101 | B3008: 婚姻与家庭 | C3008: 婚姻第三者风险 | D3008: 4 | E3008: 伴侣情绪低落时，你能敏锐察觉并主动过问吗： | F3008: 单选 | G3008: D1 | H3008: 情感投入度 | I3008: 常常后知后觉 | J3008: 2 | K3008: 对方说了我才会管 | L3008: 1 | M3008: 多数时候能留意到 | N3008: 3 | O3008: 总能第一时间发现 | P3008: 4 | S3008: =MAX(J3008,L3008,N3008,P3008) | T3008: =MIN(J3008,L3008,N3008,P3008)
A3009: 101 | B3009: 婚姻与家庭 | C3009: 婚姻第三者风险 | D3009: 5 | E3009: 你对婚姻现状的情感浓度，更接近哪种形容： | F3009: 单选 | G3009: D1 | H3009: 情感投入度 | I3009: 老夫老妻般安稳 | J3009: 3 | K3009: 时好时坏说不清 | L3009: 2 | M3009: 亲密感仍在持续升温 | N3009: 4 | O3009: 越来越像陌生人 | P3009: 1 | S3009: =MAX(J3009,L3009,N3009,P3009) | T3009: =MIN(J3009,L3009,N3009,P3009)
A3010: 101 | B3010: 婚姻与家庭 | C3010: 婚姻第三者风险 | D3010: 6 | E3010: 工作再忙，你也会专门留出陪伴伴侣的时间吗： | F3010: 单选 | G3010: D1 | H3010: 情感投入度 | I3010: 想起来才安排 | J3010: 2 | K3010: 尽量留偶尔失守 | L3010: 3 | M3010: 固定留且雷打不动 | N3010: 4 | O3010: 忙起来就完全牺牲 | P3010: 1 | S3010: =MAX(J3010,L3010,N3010,P3010) | T3010: =MIN(J3010,L3010,N3010,P3010)
A3011: 101 | B3011: 婚姻与家庭 | C3011: 婚姻第三者风险 | D3011: 7 | E3011: 身体接触（牵手拥抱等）在你们的日常中： | F3011: 单选 | G3011: D1 | H3011: 情感投入度 | I3011: 很久没有过了 | J3011: 1 | K3011: 频率不高但不排斥 | L3011: 3 | M3011: 自然发生习以为常 | N3011: 4 | O3011: 节日时才会有 | P3011: 2 | S3011: =MAX(J3011,L3011,N3011,P3011) | T3011: =MIN(J3011,L3011,N3011,P3011)
A3012: 101 | B3012: 婚姻与家庭 | C3012: 婚姻第三者风险 | D3012: 8 | E3012: 你和伴侣争吵后的和解，通常是怎么达成的： | F3012: 单选 | G3012: D1 | H3012: 情感投入度 | I3012: 拖几天才慢慢缓和 | J3012: 2 | K3012: 快速和好很快如常 | L3012: 4 | M3012: 总有一方冷淡到底 | N3012: 1 | O3012: 需要外人从中劝解 | P3012: 3 | S3012: =MAX(J3012,L3012,N3012,P3012) | T3012: =MIN(J3012,L3012,N3012,P3012)
A3013: 101 | B3013: 婚姻与家庭 | C3013: 婚姻第三者风险 | D3013: 9 | E3013: 异性同事深夜发来情绪化的倾诉消息，你会： | F3013: 单选 | G3013: D2 | H3013: 边界与自律 | I3013: 耐心陪聊到深夜 | J3013: 1 | K3013: 觉得正常正常回复 | L3013: 2 | M3013: 转告伴侣并减少私聊 | N3013: 4 | O3013: 简短回复转移话题 | P3013: 3 | S3013: =MAX(J3013,L3013,N3013,P3013) | T3013: =MIN(J3013,L3013,N3013,P3013)
A3014: 101 | B3014: 婚姻与家庭 | C3014: 婚姻第三者风险 | D3014: 10 | E3014: 有人对你表达暧昧好感时，你的处理方式是： | F3014: 单选 | G3014: D2 | H3014: 边界与自律 | I3014: 婉拒但继续做朋友 | J3014: 3 | K3014: 明确拒绝不留余地 | L3014: 4 | M3014: 享受被关注的感觉 | N3014: 1 | O3014: 装作看不懂拖着 | P3014: 2 | S3014: =MAX(J3014,L3014,N3014,P3014) | T3014: =MIN(J3014,L3014,N3014,P3014)
A3015: 101 | B3015: 婚姻与家庭 | C3015: 婚姻第三者风险 | D3015: 11 | E3015: 和异性朋友单独吃饭，你会提前告诉伴侣吗： | F3015: 单选 | G3015: D2 | H3015: 边界与自律 | I3015: 被问起才顺口一提 | J3015: 2 | K3015: 饭后随口聊起过 | L3015: 3 | M3015: 一定提前说清去处 | N3015: 4 | O3015: 从不报备觉得没必要 | P3015: 1 | S3015: =MAX(J3015,L3015,N3015,P3015) | T3015: =MIN(J3015,L3015,N3015,P3015)
... A3020: 101 | B3020: 婚姻与家庭 | C3020: 婚姻第三者风险 | D3020: 16 | E3020: 前任或旧识突然联系叙旧，你的态度是： | F3020: 单选 | G3020: D2 | H3020: 边界与自律 | I3020: 聊几句就自然断了 | J3020: 2 | K3020: 告知伴侣再决定见否 | L3020: 4 | M3020: 婉言推掉不再联系 | N3020: 3 | O3020: 背着伴侣偷偷赴约 | P3020: 1 | S3020: =MAX(J3020,L3020,N3020,P3020) | T3020: =MIN(J3020,L3020,N3020,P3020)
A3021: 101 | B3021: 婚姻与家庭 | C3021: 婚姻第三者风险 | D3021: 17 | E3021: 以下哪些做法是你平时的习惯（多选）： | F3021: 多选 | G3021: D2 | H3021: 边界与自律 | I3021: 朋友圈公开婚姻状态 | J3021: 2 | K3021: 保留暧昧对象的联系方式 | L3021: 0 | M3021: 和异性聊到深夜 | N3021: 0 | O3021: 重要聚会带上伴侣 | P3021: 2 | Q3021: 主动介绍伴侣给朋友认识 | R3021: 1 | S3021: =MAX(J3021,L3021,N3021,P3021,R3021) | T3021: =MIN(J3021,L3021,N3021,P3021,R3021)
A3022: 101 | B3022: 婚姻与家庭 | C3022: 婚姻第三者风险 | D3022: 18 | E3022: 你和伴侣之间，目前最像哪种沟通状态： | F3022: 单选 | G3022: D3 | H3022: 信任与透明 | I3022: 报喜不报忧挑着说 | J3022: 2 | K3022: 日常顺畅偶有回避 | L3022: 3 | M3022: 无话不谈彼此透明 | N3022: 4 | O3022: 各忙各的几乎无话 | P3022: 1 | S3022: =MAX(J3022,L3022,N3022,P3022) | T3022: =MIN(J3022,L3022,N3022,P3022)
A3023: 101 | B3023: 婚姻与家庭 | C3023: 婚姻第三者风险 | D3023: 19 | E3023: 你怀疑过伴侣对你隐瞒某件重要的事吗： | F3023: 单选 | G3023: D3 | H3023: 信任与透明 | I3023: 从没起过这种疑心 | J3023: 4 | K3023: 常有说不清的疑虑 | L3023: 1 | M3023: 疑过一次后来澄清 | N3023: 3 | O3023: 偶尔犯嘀咕没证据 | P3023: 2 | S3023: =MAX(J3023,L3023,N3023,P3023) | T3023: =MIN(J3023,L3023,N3023,P3023)
A3024: 101 | B3024: 婚姻与家庭 | C3024: 婚姻第三者风险 | D3024: 20 | E3024: 伴侣翻看你的行程或消费记录时，你的感觉： | F3024: 单选 | G3024: D3 | H3024: 信任与透明 | I3024: 理解这是在乎的表现 | J3024: 3 | K3024: 坦然透明不怕查 | L3024: 4 | M3024: 心虚会下意识遮挡 | N3024: 1 | O3024: 有点烦但能接受 | P3024: 2 | S3024: =MAX(J3024,L3024,N3024,P3024) | T3024: =MIN(J3024,L3024,N3024,P3024)
A3025: 101 | B3025: 婚姻与家庭 | C3025: 婚姻第三者风险 | D3025: 21 | E3025: 当伴侣主动谈及感情危机的话题（如安全感），你会： | F3025: 单选 | G3025: D3 | H3025: 信任与透明 | I3025: 敷衍几句岔开话题 | J3025: 1 | K3025: 认真回应一起面对 | L3025: 4 | M3025: 先听完再表达想法 | N3025: 3 | O3025: 觉得对方想太多了 | P3025: 2 | S3025: =MAX(J3025,L3025,N3025,P3025) | T3025: =MIN(J3025,L3025,N3025,P3025)
A3026: 101 | B3026: 婚姻与家庭 | C3026: 婚姻第三者风险 | D3026: 22 | E3026: 你和伴侣对各自社交圈的了解程度是： | F3026: 单选 | G3026: D3 | H3026: 信任与透明 | I3026: 互不干涉一无所知 | J3026: 1 | K3026: 彼此的朋友都认识 | L3026: 4 | M3026: 只知名字没见过面 | N3026: 2 | O3026: 熟悉常提的那几位 | P3026: 3 | S3026: =MAX(J3026,L3026,N3026,P3026) | T3026: =MIN(J3026,L3026,N3026,P3026)
A3027: 101 | B3027: 婚姻与家庭 | C3027: 婚姻第三者风险 | D3027: 23 | E3027: 以下哪些情况符合你们目前的相处（多选）： | F3027: 多选 | G3027: D3 | H3027: 信任与透明 | I3027: 各有不愿提的秘密 | J3027: 0 | K3027: 大额消费互相知会 | L3027: 2 | M3027: 偶尔互看手机开玩笑 | N3027: 1 | O3027: 出行互相告知行程 | P3027: 2 | Q3027: 查岗是常态相处方式 | R3027: 0 | S3027: =MAX(J3027,L3027,N3027,P3027,R3027) | T3027: =MIN(J3027,L3027,N3027,P3027,R3027)
A3028: 101 | B3028: 婚姻与家庭 | C3028: 婚姻第三者风险 | D3028: 24 | E3028: 如果发现伴侣与异性走得近，你会先做什么： | F3028: 单选 | G3028: D3 | H3028: 信任与透明 | I3028: 先质问再翻手机验证 | J3028: 1 | K3028: 憋在心里自己消化 | L3028: 3 | M3028: 直接谈感受而非定罪 | N3028: 4 | O3028: 冷战试探等对方解释 | P3028: 2 | S3028: =MAX(J3028,L3028,N3028,P3028) | T3028: =MIN(J3028,L3028,N3028,P3028)
A3029: 102 | B3029: 婚姻与家庭 | C3029: 婆媳关系 | D3029: 1 | E3029: 婆婆不打招呼上门收拾你们的小家，你会： | F3029: 单选 | G3029: D1 | H3029: 边界与分寸 | I3029: 笑着接受心里憋屈 | J3029: 2 | K3029: 当面顶回去不留情面 | L3029: 1 | M3029: 事后让伴侣去沟通 | N3029: 3 | O3029: 当面表达希望先商量 | P3029: 4 | S3029: =MAX(J3029,L3029,N3029,P3029) | T3029: =MIN(J3029,L3029,N3029,P3029)
A3030: 102 | B3030: 婚姻与家庭 | C3030: 婆媳关系 | D3030: 2 | E3030: 婆婆对小家庭的花销指手画脚，你的做法是： | F3030: 单选 | G3030: D1 | H3030: 边界与分寸 | I3030: 当场反驳让她下不来台 | J3030: 1 | K3030: 明确这是小家的私事 | L3030: 4 | M3030: 左耳进右耳出不理会 | N3030: 3 | O3030: 默默忍受越积越多 | P3030: 2 | S3030: =MAX(J3030,L3030,N3030,P3030) | T3030: =MIN(J3030,L3030,N3030,P3030)
A3031: 102 | B3031: 婚姻与家庭 | C3031: 婆媳关系 | D3031: 3 | E3031: 关于是否同住或同小区，你倾向的安排是： | F3031: 单选 | G3031: D1 | H3031: 边界与分寸 | I3031: 保持一碗汤的距离 | J3031: 4 | K3031: 同住方便互相照应 | L3031: 3 | M3031: 同住但各管各的区域 | N3031: 2 | O3031: 离得越远越清净 | P3031: 1 | S3031: =MAX(J3031,L3031,N3031,P3031) | T3031: =MIN(J3031,L3031,N3031,P3031)
A3032: 102 | B3032: 婚姻与家庭 | C3032: 婆媳关系 | D3032: 4 | E3032: 婆婆总用老经验带孙辈，你通常会： | F3032: 单选 | G3032: D1 | H3032: 边界与分寸 | I3032: 坚持自己原则当场争执 | J3032: 2 | K3032: 睁只眼闭只眼随她去 | L3032: 1 | M3032: 私下请伴侣出面协调 | N3032: 3 | O3032: 给资料找医生证明观点 | P3032: 4 | S3032: =MAX(J3032,L3032,N3032,P3032) | T3032: =MIN(J3032,L3032,N3032,P3032)
A3033: 102 | B3033: 婚姻与家庭 | C3033: 婆媳关系 | D3033: 5 | E3033: 婆婆想保管你们的工资卡或存折，你会： | F3033: 单选 | G3033: D1 | H3033: 边界与分寸 | I3033: 直接拒绝语气生硬 | J3033: 2 | K3033: 商量折中部分参与 | L3033: 3 | M3033: 怕伤和气只好交出 | N3033: 1 | O3033: 婉言拒绝财务独立 | P3033: 4 | S3033: =MAX(J3033,L3033,N3033,P3033) | T3033: =MIN(J3033,L3033,N3033,P3033)
A3034: 102 | B3034: 婚姻与家庭 | C3034: 婆媳关系 | D3034: 6 | E3034: 婆婆对你的个人生活习惯（作息消费等）经常点评，你： | F3034: 单选 | G3034: D1 | H3034: 边界与分寸 | I3034: 全盘照做求个太平 | J3034: 1 | K3034: 感谢关心划清范围 | L3034: 4 | M3034: 据理力争寸步不让 | N3034: 2 | O3034: 微笑听着不改也不恼 | P3034: 3 | S3034: =MAX(J3034,L3034,N3034,P3034) | T3034: =MIN(J3034,L3034,N3034,P3034)
A3035: 102 | B3035: 婚姻与家庭 | C3035: 婆媳关系 | D3035: 7 | E3035: 小家庭的钥匙，你愿意长期交给婆婆吗： | F3035: 单选 | G3035: D1 | H3035: 边界与分寸 | I3035: 绝对不行毫无商量 | J3035: 2 | K3035: 商量着给备用钥匙 | L3035: 4 | M3035: 愿意方便她帮忙 | N3035: 3 | O3035: 她要就给不敢说不 | P3035: 1 | S3035: =MAX(J3035,L3035,N3035,P3035) | T3035: =MIN(J3035,L3035,N3035,P3035)
A3036: 102 | B3036: 婚姻与家庭 | C3036: 婆媳关系 | D3036: 8 | E3036: 以下哪些边界做法你能做到（多选）： | F3036: 多选 | G3036: D1 | H3036: 边界与分寸 | I3036: 重大决定先小家内部商量 | J3036: 2 | K3036: 老人说什么都照办 | L3036: 0 | M3036: 不与婆婆同住一屋 | N3036: 1 | O3036: 各自父母各自主要联络 | P3036: 1 | Q3036: 夫妻矛盾不搬婆婆救兵 | R3036: 2 | S3036: =MAX(J3036,L3036,N3036,P3036,R3036) | T3036: =MIN(J3036,L3036,N3036,P3036,R3036)
A3037: 102 | B3037: 婚姻与家庭 | C3037: 婆媳关系 | D3037: 9 | E3037: 婆婆当亲戚面数落你，你会当场如何反应： | F3037: 单选 | G3037: D2 | H3037: 沟通与缓冲 | I3037: 当场翻脸让她难堪 | J3037: 1 | K3037: 忍下不发作回房生气 | L3037: 2 | M3037: 用玩笑轻轻化解 | N3037: 3 | O3037: 笑着接住事后沟通 | P3037: 4 | S3037: =MAX(J3037,L3037,N3037,P3037) | T3037: =MIN(J3037,L3037,N3037,P3037)
A3038: 102 | B3038: 婚姻与家庭 | C3038: 婆媳关系 | D3038: 10 | E3038: 你和婆婆意见不合时，最常用的沟通方式是： | F3038: 单选 | G3038: D2 | H3038: 沟通与缓冲 | I3038: 让伴侣当传话筒 | J3038: 3 | K3038: 憋着不沟通被动等 | L3038: 1 | M3038: 挑她心情好时当面聊 | N3038: 4 | O3038: 微信文字谨慎沟通 | P3038: 2 | S3038: =MAX(J3038,L3038,N3038,P3038) | T3038: =MIN(J3038,L3038,N3038,P3038)
A3039: 102 | B3039: 婚姻与家庭 | C3039: 婆媳关系 | D3039: 11 | E3039: 婆婆插手你们夫妻争吵时，你会： | F3039: 单选 | G3039: D2 | H3039: 沟通与缓冲 | I3039: 先停战改天再谈 | J3039: 3 | K3039: 拉她评理站队互相指责 | L3039: 1 | M3039: 请她回房并单独安抚 | N3039: 4 | O3039: 任她参与不敢劝阻 | P3039: 2 | S3039: =MAX(J3039,L3039,N3039,P3039) | T3039: =MIN(J3039,L3039,N3039,P3039)
A3040: 102 | B3040: 婚姻与家庭 | C3040: 婆媳关系 | D3040: 12 | E3040: 你希望伴侣在婆媳矛盾中扮演的角色是： | F3040: 单选 | G3040: D2 | H3040: 沟通与缓冲 | I3040: 装聋作哑两不沾 | J3040: 2 | K3040: 完全帮着婆婆压我 | L3040: 1 | M3040: 挡在中间扛主要责任 | N3040: 3 | O3040: 居中传话明确立场 | P3040: 4 | S3040: =MAX(J3040,L3040,N3040,P3040) | T3040: =MIN(J3040,L3040,N3040,P3040)
A3041: 102 | B3041: 婚姻与家庭 | C3041: 婆媳关系 | D3041: 13 | E3041: 被婆婆误解冤枉后，你的第一反应是： | F3041: 单选 | G3041: D2 | H3041: 沟通与缓冲 | I3041: 向伴侣诉苦求安慰 | J3041: 2 | K3041: 憋着委屈等她自省 | L3041: 1 | M3041: 尽快找机会当面澄清 | N3041: 4 | O3041: 请伴侣帮着转达解释 | P3041: 3 | S3041: =MAX(J3041,L3041,N3041,P3041) | T3041: =MIN(J3041,L3041,N3041,P3041)
A3042: 102 | B3042: 婚姻与家庭 | C3042: 婆媳关系 | D3042: 14 | E3042: 婆婆在背后向亲戚抱怨你，你知道后会： | F3042: 单选 | G3042: D2 | H3042: 沟通与缓冲 | I3042: 找人评理对质到底 | J3042: 1 | K3042: 不点破但心防加深 | L3042: 2 | M3042: 当面委婉表达感受 | N3042: 4 | O3042: 从此减少往来避嫌 | P3042: 3 | S3042: =MAX(J3042,L3042,N3042,P3042) | T3042: =MIN(J3042,L3042,N3042,P3042)
A3043: 102 | B3043: 婚姻与家庭 | C3043: 婆媳关系 | D3043: 15 | E3043: 和婆婆说话时，你会刻意注意措辞和语气吗： | F3043: 单选 | G3043: D2 | H3043: 沟通与缓冲 | I3043: 客气为主偶尔直率 | J3043: 3 | K3043: 能忍则忍尽量少说 | L3043: 2 | M3043: 会选时机也讲究方式 | N3043: 4 | O3043: 想起什么就说什么 | P3043: 1 | S3043: =MAX(J3043,L3043,N3043,P3043) | T3043: =MIN(J3043,L3043,N3043,P3043)
A3044: 102 | B3044: 婚姻与家庭 | C3044: 婆媳关系 | D3044: 16 | E3044: 婆婆提出让你为难的要求时，你的应对是： | F3044: 单选 | G3044: D2 | H3044: 沟通与缓冲 | I3044: 勉强答应事后生闷气 | J3044: 1 | K3044: 含糊拖延不了了之 | L3044: 3 | M3044: 硬邦邦直接说不 | N3044: 2 | O3044: 先肯定难处再提替代 | P3044: 4 | S3044: =MAX(J3044,L3044,N3044,P3044) | T3044: =MIN(J3044,L3044,N3044,P3044)
A3045: 102 | B3045: 婚姻与家庭 | C3045: 婆媳关系 | D3045: 17 | E3045: 以下哪些缓和婆媳关系的招数你愿意用（多选）： | F3045: 多选 | G3045: D2 | H3045: 沟通与缓冲 | I3045: 冷处理长期不往来 | J3045: 0 | K3045: 记住她爱吃的菜 | L3045: 1 | M3045: 节日备一份小礼物 | N3045: 2 | O3045: 拉着全家评理对错 | P3045: 0 | Q3045: 当面从不拆她面子 | R3045: 2 | S3045: =MAX(J3045,L3045,N3045,P3045,R3045) | T3045: =MIN(J3045,L3045,N3045,P3045,R3045)
A3046: 102 | B3046: 婚姻与家庭 | C3046: 婆媳关系 | D3046: 18 | E3046: 你能理解婆婆那些做法背后的时代局限吗： | F3046: 单选 | G3046: D3 | H3046: 理解与联结 | I3046: 她的动机全是恶意 | J3046: 1 | K3046: 常能体谅她的不易 | L3046: 4 | M3046: 很少去想只想对错 | N3046: 2 | O3046: 偶尔能想得通 | P3046: 3 | S3046: =MAX(J3046,L3046,N3046,P3046) | T3046: =MIN(J3046,L3046,N3046,P3046)
A3047: 102 | B3047: 婚姻与家庭 | C3047: 婆媳关系 | D3047: 19 | E3047: 你会主动关心婆婆的身体和喜好吗： | F3047: 单选 | G3047: D3 | H3047: 理解与联结 | I3047: 她先示好我才有回应 | J3047: 2 | K3047: 常问常买如对亲妈 | L3047: 4 | M3047: 节日做到礼数周全 | N3047: 3 | O3047: 从没想过要关心她 | P3047: 1 | S3047: =MAX(J3047,L3047,N3047,P3047) | T3047: =MIN(J3047,L3047,N3047,P3047)
A3048: 102 | B3048: 婚姻与家庭 | C3048: 婆媳关系 | D3048: 20 | E3048: 婆婆做的饭菜不合口味，你会： | F3048: 单选 | G3048: D3 | H3048: 理解与联结 | I3048: 当面挑刺让她改 | J3048: 1 | K3048: 让伴侣转达口味偏好 | L3048: 3 | M3048: 先夸用心再提口味 | N3048: 4 | O3048: 默默吃少说为妙 | P3048: 2 | S3048: =MAX(J3048,L3048,N3048,P3048) | T3048: =MIN(J3048,L3048,N3048,P3048)
A3049: 102 | B3049: 婚姻与家庭 | C3049: 婆媳关系 | D3049: 21 | E3049: 婆婆生病需要照顾时，你的态度是： | F3049: 单选 | G3049: D3 | H3049: 理解与联结 | I3049: 以忙碌为由能躲则躲 | J3049: 1 | K3049: 出钱不出力保持距离 | L3049: 2 | M3049: 和伴侣商量合理分工 | N3049: 3 | O3049: 主动分担出力出钱 | P3049: 4 | S3049: =MAX(J3049,L3049,N3049,P3049) | T3049: =MIN(J3049,L3049,N3049,P3049)
A3050: 102 | B3050: 婚姻与家庭 | C3050: 婆媳关系 | D3050: 22 | E3050: 你在心里如何看待婆婆这个身份： | F3050: 单选 | G3050: D3 | H3050: 理解与联结 | I3050: 天生的对立面敌人 | J3050: 1 | K3050: 处得来就处不来拉倒 | L3050: 3 | M3050: 是需要经营的家人 | N3050: 4 | O3050: 只是丈夫的亲戚 | P3050: 2 | S3050: =MAX(J3050,L3050,N3050,P3050) | T3050: =MIN(J3050,L3050,N3050,P3050)
A3051: 102 | B3051: 婚姻与家庭 | C3051: 婆媳关系 | D3051: 23 | E3051: 婆婆夸你或对你示好时，你的回应是： | F3051: 单选 | G3051: D3 | H3051: 理解与联结 | I3051: 客气回应保持距离 | J3051: 3 | K3051: 自然接受并回以善意 | L3051: 4 | M3051: 怀疑她别有所图 | N3051: 1 | O3051: 嘴上谢谢心里不服 | P3051: 2 | S3051: =MAX(J3051,L3051,N3051,P3051) | T3051: =MIN(J3051,L3051,N3051,P3051)
A3052: 102 | B3052: 婚姻与家庭 | C3052: 婆媳关系 | D3052: 24 | E3052: 你愿意把婆婆的付出看在眼里并说出口吗： | F3052: 单选 | G3052: D3 | H3052: 理解与联结 | I3052: 她做得远远不够 | J3052: 1 | K3052: 心里记得嘴上不说 | L3052: 3 | M3052: 觉得都是应该的 | N3052: 2 | O3052: 经常当面感谢她 | P3052: 4 | S3052: =MAX(J3052,L3052,N3052,P3052) | T3052: =MIN(J3052,L3052,N3052,P3052)
A3053: 103 | B3053: 婚姻与家庭 | C3053: 家庭氛围与家庭关系 | D3053: 1 | E3053: 一天中全家人聚在一起聊天的场景，通常是： | F3053: 单选 | G3053: D1 | H3053: 温馨互动 | I3053: 晚饭后自然聊上一阵 | J3053: 4 | K3053: 各回各屋少有交集 | L3053: 1 | M3053: 边看电视边零星说几句 | N3053: 3 | O3053: 有事才开口说事 | P3053: 2 | S3053: =MAX(J3053,L3053,N3053,P3053) | T3053: =MIN(J3053,L3053,N3053,P3053)
A3054: 103 | B3054: 婚姻与家庭 | C3054: 家庭氛围与家庭关系 | D3054: 2 | E3054: 家里有没有大家都在意的小仪式（生日聚餐等）： | F3054: 单选 | G3054: D1 | H3054: 温馨互动 | I3054: 偶尔想起来才办 | J3054: 2 | K3054: 雷打不动代代相传 | L3054: 4 | M3054: 有几个简单的小仪式 | N3054: 3 | O3054: 从没有过这类传统 | P3054: 1 | S3054: =MAX(J3054,L3054,N3054,P3054) | T3054: =MIN(J3054,L3054,N3054,P3054)
A3055: 103 | B3055: 婚姻与家庭 | C3055: 家庭氛围与家庭关系 | D3055: 3 | E3055: 回忆里全家一起大笑的画面，最近出现在： | F3055: 单选 | G3055: D1 | H3055: 温馨互动 | I3055: 已经想不起来 | J3055: 1 | K3055: 半年前的某个场合 | L3055: 2 | M3055: 这几天或这一周 | N3055: 4 | O3055: 最近一两个月 | P3055: 3 | S3055: =MAX(J3055,L3055,N3055,P3055) | T3055: =MIN(J3055,L3055,N3055,P3055)
A3056: 103 | B3056: 婚姻与家庭 | C3056: 家庭氛围与家庭关系 | D3056: 4 | E3056: 家里的家务活，实际的状态更接近： | F3056: 单选 | G3056: D1 | H3056: 温馨互动 | I3056: 谁看不下去谁做 | J3056: 2 | K3056: 固定一人默默包揽 | L3056: 1 | M3056: 抢着做互相搭手 | N3056: 4 | O3056: 有分工偶尔互相补位 | P3056: 3 | S3056: =MAX(J3056,L3056,N3056,P3056) | T3056: =MIN(J3056,L3056,N3056,P3056)
A3057: 103 | B3057: 婚姻与家庭 | C3057: 家庭氛围与家庭关系 | D3057: 5 | E3057: 你心情好时会把家里的事当趣闻分享给谁： | F3057: 单选 | G3057: D1 | H3057: 温馨互动 | I3057: 家是唯一不想分享的地方 | J3057: 1 | K3057: 家人是我的首选听众 | L3057: 4 | M3057: 看话题在家和朋友间选 | N3057: 3 | O3057: 宁可选朋友也不在家说 | P3057: 2 | S3057: =MAX(J3057,L3057,N3057,P3057) | T3057: =MIN(J3057,L3057,N3057,P3057)
... A3059: 103 | B3059: 婚姻与家庭 | C3059: 家庭氛围与家庭关系 | D3059: 7 | E3059: 推开门回到家，家里的第一感觉通常是： | F3059: 单选 | G3059: D1 | H3059: 温馨互动 | I3059: 放松踏实像充电 | J3059: 4 | K3059: 平淡没什么感觉 | L3059: 2 | M3059: 热闹但有点吵闹 | N3059: 3 | O3059: 冷清得像旅馆 | P3059: 1 | S3059: =MAX(J3059,L3059,N3059,P3059) | T3059: =MIN(J3059,L3059,N3059,P3059)
A3060: 103 | B3060: 婚姻与家庭 | C3060: 家庭氛围与家庭关系 | D3060: 8 | E3060: 以下哪些温馨场景你家出现过（多选）： | F3060: 多选 | G3060: D1 | H3060: 温馨互动 | I3060: 饭后散步闲聊 | J3060: 2 | K3060: 翻看老照片聊往事 | L3060: 1 | M3060: 为成员成就庆祝过 | N3060: 2 | O3060: 一起做一顿饭 | P3060: 2 | Q3060: 全家各玩各的手机 | R3060: 0 | S3060: =MAX(J3060,L3060,N3060,P3060,R3060) | T3060: =MIN(J3060,L3060,N3060,P3060,R3060)
A3061: 103 | B3061: 婚姻与家庭 | C3061: 家庭氛围与家庭关系 | D3061: 9 | E3061: 家里出现分歧（如消费观念）时，通常： | F3061: 单选 | G3061: D2 | H3061: 冲突与情绪 | I3061: 长辈拍板其他人配合 | J3061: 3 | K3061: 各执一词不欢而散 | L3061: 2 | M3061: 摆事实商量出折中 | N3061: 4 | O3061: 谁嗓门大听谁的 | P3061: 1 | S3061: =MAX(J3061,L3061,N3061,P3061) | T3061: =MIN(J3061,L3061,N3061,P3061)
A3062: 103 | B3062: 婚姻与家庭 | C3062: 家庭氛围与家庭关系 | D3062: 10 | E3062: 家里有人发脾气时，其他人的反应通常是： | F3062: 单选 | G3062: D2 | H3062: 冲突与情绪 | I3062: 先安抚等平静再谈 | J3062: 4 | K3062: 事后有人去打圆场 | L3062: 3 | M3062: 跟着上火对吵起来 | N3062: 1 | O3062: 躲开回避装没看见 | P3062: 2 | S3062: =MAX(J3062,L3062,N3062,P3062) | T3062: =MIN(J3062,L3062,N3062,P3062)
A3063: 103 | B3063: 婚姻与家庭 | C3063: 家庭氛围与家庭关系 | D3063: 11 | E3063: 家人犯错（打碎东西考砸等）时，第一句话通常是： | F3063: 单选 | G3063: D2 | H3063: 冲突与情绪 | I3063: 说几句就翻篇了 | J3063: 3 | K3063: 劈头盖脸先骂一顿 | L3063: 1 | M3063: 人没事吧比事重要 | N3063: 4 | O3063: 冷嘲热讽翻旧账 | P3063: 2 | S3063: =MAX(J3063,L3063,N3063,P3063) | T3063: =MIN(J3063,L3063,N3063,P3063)
A3064: 103 | B3064: 婚姻与家庭 | C3064: 家庭氛围与家庭关系 | D3064: 12 | E3064: 家里吵过的架，一般以什么方式收场： | F3064: 单选 | G3064: D2 | H3064: 冲突与情绪 | I3064: 冷战几天自然忘记 | J3064: 2 | K3064: 谁都不提永远翻篇 | L3064: 1 | M3064: 当天说开互相道歉 | N3064: 4 | O3064: 有人牵头复盘和解 | P3064: 3 | S3064: =MAX(J3064,L3064,N3064,P3064) | T3064: =MIN(J3064,L3064,N3064,P3064)
A3065: 103 | B3065: 婚姻与家庭 | C3065: 家庭氛围与家庭关系 | D3065: 13 | E3065: 家庭成员之间会说对不起和谢谢吗： | F3065: 单选 | G3065: D2 | H3065: 冲突与情绪 | I3065: 从没听家人说过 | J3065: 1 | K3065: 只在特别严重的时刻 | L3065: 2 | M3065: 常说出口习以为常 | N3065: 4 | O3065: 偶尔说有点别扭 | P3065: 3 | S3065: =MAX(J3065,L3065,N3065,P3065) | T3065: =MIN(J3065,L3065,N3065,P3065)
A3066: 103 | B3066: 婚姻与家庭 | C3066: 家庭氛围与家庭关系 | D3066: 14 | E3066: 家里讨论敏感话题（成绩收入婚恋）时，气氛通常： | F3066: 单选 | G3066: D2 | H3066: 冲突与情绪 | I3066: 能坦诚聊不挖苦不逼问 | J3066: 4 | K3066: 心照不宣绕着走 | L3066: 2 | M3066: 能聊但容易说崩 | N3066: 3 | O3066: 一开口就变批斗会 | P3066: 1 | S3066: =MAX(J3066,L3066,N3066,P3066) | T3066: =MIN(J3066,L3066,N3066,P3066)
A3067: 103 | B3067: 婚姻与家庭 | C3067: 家庭氛围与家庭关系 | D3067: 15 | E3067: 在外受了委屈，你愿意对家人吐露吗： | F3067: 单选 | G3067: D2 | H3067: 冲突与情绪 | I3067: 怕被数落宁可不提 | J3067: 1 | K3067: 愿意家人会接住我 | L3067: 4 | M3067: 会提但做好被唠叨准备 | N3067: 3 | O3067: 说一半留一半 | P3067: 2 | S3067: =MAX(J3067,L3067,N3067,P3067) | T3067: =MIN(J3067,L3067,N3067,P3067)
A3068: 103 | B3068: 婚姻与家庭 | C3068: 家庭氛围与家庭关系 | D3068: 16 | E3068: 家庭重大矛盾僵持不下时，通常谁先让步： | F3068: 单选 | G3068: D2 | H3068: 冲突与情绪 | I3068: 永远是最弱势的人 | J3068: 1 | K3068: 各退一步轮流示好 | L3068: 3 | M3068: 有人主动破冰顾大局 | N3068: 4 | O3068: 拖到不了了之 | P3068: 2 | S3068: =MAX(J3068,L3068,N3068,P3068) | T3068: =MIN(J3068,L3068,N3068,P3068)
A3069: 103 | B3069: 婚姻与家庭 | C3069: 家庭氛围与家庭关系 | D3069: 17 | E3069: 你遇到大困难时，家里的实际反应是： | F3069: 单选 | G3069: D3 | H3069: 支持与归属 | I3069: 口头安慰实际帮不上 | J3069: 2 | K3069: 先怪我怎么搞成这样 | L3069: 1 | M3069: 量力而行帮一些 | N3069: 3 | O3069: 第一时间出钱出力出主意 | P3069: 4 | S3069: =MAX(J3069,L3069,N3069,P3069) | T3069: =MIN(J3069,L3069,N3069,P3069)
A3070: 103 | B3070: 婚姻与家庭 | C3070: 家庭氛围与家庭关系 | D3070: 18 | E3070: 家里做出的重大决定（买房搬迁等），你感觉： | F3070: 单选 | G3070: D3 | H3070: 支持与归属 | I3070: 我被通知结果而已 | J3070: 1 | K3070: 有人问过我但没被采纳 | L3070: 2 | M3070: 我的意见被认真听取 | N3070: 4 | O3070: 大体商量过还算顺心 | P3070: 3 | S3070: =MAX(J3070,L3070,N3070,P3070) | T3070: =MIN(J3070,L3070,N3070,P3070)
A3071: 103 | B3071: 婚姻与家庭 | C3071: 家庭氛围与家庭关系 | D3071: 19 | E3071: 当家人想坚持自己的选择时，家里的态度是： | F3071: 单选 | G3071: D3 | H3071: 支持与归属 | I3071: 半信半疑看着再说 | J3071: 3 | K3071: 嘴上不说心里记恨 | L3071: 2 | M3071: 强烈反对直到服从为止 | N3071: 1 | O3071: 支持并提醒可能的风险 | P3071: 4 | S3071: =MAX(J3071,L3071,N3071,P3071) | T3071: =MIN(J3071,L3071,N3071,P3071)
A3072: 103 | B3072: 婚姻与家庭 | C3072: 家庭氛围与家庭关系 | D3072: 20 | E3072: 家人的成就在家里会被怎样对待： | F3072: 单选 | G3072: D3 | H3072: 支持与归属 | I3072: 被拿来和别人家比较 | J3072: 1 | K3072: 真心骄傲并庆祝 | L3072: 4 | M3072: 夸一句马上泼冷水 | N3072: 2 | O3072: 平静接受不冷不热 | P3072: 3 | S3072: =MAX(J3072,L3072,N3072,P3072) | T3072: =MIN(J3072,L3072,N3072,P3072)
... A3074: 103 | B3074: 婚姻与家庭 | C3074: 家庭氛围与家庭关系 | D3074: 22 | E3074: 当你和外部世界发生冲突时，家的角色是： | F3074: 单选 | G3074: D3 | H3074: 支持与归属 | I3074: 先审问我是不是我的错 | J3074: 1 | K3074: 让我自己解决别添乱 | L3074: 2 | M3074: 无论如何都站在我这边 | N3074: 4 | O3074: 帮我分析给建议 | P3074: 3 | S3074: =MAX(J3074,L3074,N3074,P3074) | T3074: =MIN(J3074,L3074,N3074,P3074)
A3075: 103 | B3075: 婚姻与家庭 | C3075: 家庭氛围与家庭关系 | D3075: 23 | E3075: 以下哪些描述符合你与家人的关系（多选）： | F3075: 多选 | G3075: D3 | H3075: 支持与归属 | I3075: 信任彼此的忠诚 | J3075: 2 | K3075: 聚在一起就互相挑剔 | L3075: 0 | M3075: 对旧矛盾仍心有余悸 | N3075: 1 | O3075: 能坦然表达爱意 | P3075: 2 | Q3075: 有事第一个想到家人 | R3075: 2 | S3075: =MAX(J3075,L3075,N3075,P3075,R3075) | T3075: =MIN(J3075,L3075,N3075,P3075,R3075)
A3076: 103 | B3076: 婚姻与家庭 | C3076: 家庭氛围与家庭关系 | D3076: 24 | E3076: 你对这个家的整体归属感，打分的话会打： | F3076: 单选 | G3076: D3 | H3076: 支持与归属 | I3076: 一般谈不上多深 | J3076: 2 | K3076: 比较高有牵挂在 | L3076: 3 | M3076: 很高是我最深的根基 | N3076: 4 | O3076: 很低渴望早点逃离 | P3076: 1 | S3076: =MAX(J3076,L3076,N3076,P3076) | T3076: =MIN(J3076,L3076,N3076,P3076)
A3077: 104 | B3077: 婚姻与家庭 | C3077: 原生家庭与童年创伤 | D3077: 1 | E3077: 回忆小时候，你的委屈和难过通常被家人如何对待： | F3077: 单选 | G3077: D1 | H3077: 情感忽视印记 | I3077: 被说矫情不许哭 | J3077: 1 | K3077: 被看见被耐心安抚 | L3077: 4 | M3077: 没人注意自己消化 | N3077: 2 | O3077: 有安慰但很敷衍 | P3077: 3 | S3077: =MAX(J3077,L3077,N3077,P3077) | T3077: =MIN(J3077,L3077,N3077,P3077)
A3078: 104 | B3078: 婚姻与家庭 | C3078: 原生家庭与童年创伤 | D3078: 2 | E3078: 小时候你取得成绩时，家里的反应通常是： | F3078: 单选 | G3078: D1 | H3078: 情感忽视印记 | I3078: 真心为你高兴 | J3078: 4 | K3078: 从不提起你的存在感低 | L3078: 1 | M3078: 淡淡夸一句就过了 | N3078: 3 | O3078: 被拿来和别人比较 | P3078: 2 | S3078: =MAX(J3078,L3078,N3078,P3078) | T3078: =MIN(J3078,L3078,N3078,P3078)
A3079: 104 | B3079: 婚姻与家庭 | C3079: 原生家庭与童年创伤 | D3079: 3 | E3079: 儿时你能否自由地在家里表达不同意见： | F3079: 单选 | G3079: D1 | H3079: 情感忽视印记 | I3079: 可以且会被认真对待 | J3079: 4 | K3079: 多数时候可以表达 | L3079: 3 | M3079: 说了会被骂或被无视 | N3079: 1 | O3079: 偶尔说安全偶尔危险 | P3079: 2 | S3079: =MAX(J3079,L3079,N3079,P3079) | T3079: =MIN(J3079,L3079,N3079,P3079)
A3080: 104 | B3080: 婚姻与家庭 | C3080: 原生家庭与童年创伤 | D3080: 4 | E3080: 小时候家里人对你的陪伴状态更接近： | F3080: 单选 | G3080: D1 | H3080: 情感忽视印记 | I3080: 忙碌但关键场合都在 | J3080: 3 | K3080: 常有高质量的陪伴 | L3080: 4 | M3080: 常年缺席或人在心不在 | N3080: 1 | O3080: 偶尔陪伴多数独处 | P3080: 2 | S3080: =MAX(J3080,L3080,N3080,P3080) | T3080: =MIN(J3080,L3080,N3080,P3080)
...

Sheet 维度设置
A1: 主题序号 | B1: 测评主题 | C1: 维度代码 | D1: 维度名称 | E1: 维度说明 | F1: 题目数 | G1: 包含题号 | H1: 维度最低分 | I1: 维度总分
A2: 1 | B2: MBTI 16型人格 | C2: D1 | D2: 能量取向 | E2: 在独处充电与社交互动间的精力偏好，高分偏外向。 | F2: =COUNTIFS(题目明细!$A:$A,A2,题目明细!$G:$G,C2) | G2: 1、2、3、4、5、6、7、8、9、10、11、12、13、14、15、16、17、18、19、20、21、22 | H2: =SUMIFS(题目明细!$T:$T,题目明细!$A:$A,A2,题目明细!$G:$G,C2) | I2: =SUMIFS(题目明细!$S:$S,题目明细!$A:$A,A2,题目明细!$G:$G,C2)
A3: 1 | B3: MBTI 16型人格 | C3: D2 | D3: 信息获取 | E3: 接收信息时偏重事实细节还是联想与可能，高分偏直觉。 | F3: =COUNTIFS(题目明细!$A:$A,A3,题目明细!$G:$G,C3) | G3: 23、24、25、26、27、28、29、30、31、32、33、34、35、36、37、38、39、40、41、42、43、44 | H3: =SUMIFS(题目明细!$T:$T,题目明细!$A:$A,A3,题目明细!$G:$G,C3) | I3: =SUMIFS(题目明细!$S:$S,题目明细!$A:$A,A3,题目明细!$G:$G,C3)
A4: 1 | B4: MBTI 16型人格 | C4: D3 | D4: 决策方式 | E4: 做判断时偏重逻辑一致还是人际情感，高分偏情感。 | F4: =COUNTIFS(题目明细!$A:$A,A4,题目明细!$G:$G,C4) | G4: 45、46、47、48、49、50、51、52、53、54、55、56、57、58、59、60、61、62、63、64、65、66 | H4: =SUMIFS(题目明细!$T:$T,题目明细!$A:$A,A4,题目明细!$G:$G,C4) | I4: =SUMIFS(题目明细!$S:$S,题目明细!$A:$A,A4,题目明细!$G:$G,C4)
A5: 1 | B5: MBTI 16型人格 | C5: D4 | D5: 生活态度 | E5: 对待计划、秩序与变化的基本倾向，高分偏计划性。 | F5: =COUNTIFS(题目明细!$A:$A,A5,题目明细!$G:$G,C5) | G5: 67、68、69、70、71、72、73、74、75、76、77、78、79、80、81、82、83、84、85、86、87、88 | H5: =SUMIFS(题目明细!$T:$T,题目明细!$A:$A,A5,题目明细!$G:$G,C5) | I5: =SUMIFS(题目明细!$S:$S,题目明细!$A:$A,A5,题目明细!$G:$G,C5)
A6: 2 | B6: MBTI维度细分（I/E、S/N、T/F、J/P） | C6: D1 | D6: 能量来源 | E6: 精力主要来自独处还是人群互动，高分偏外向。 | F6: =COUNTIFS(题目明细!$A:$A,A6,题目明细!$G:$G,C6) | G6: 1、2、3、4、5、6、7、8、9、10 | H6: =SUMIFS(题目明细!$T:$T,题目明细!$A:$A,A6,题目明细!$G:$G,C6) | I6: =SUMIFS(题目明细!$S:$S,题目明细!$A:$A,A6,题目明细!$G:$G,C6)
A7: 2 | B7: MBTI维度细分（I/E、S/N、T/F、J/P） | C7: D2 | D7: 感知偏好 | E7: 接收信息时偏重具体经验还是联想可能，高分偏直觉。 | F7: =COUNTIFS(题目明细!$A:$A,A7,题目明细!$G:$G,C7) | G7: 11、12、13、14、15、16、17、18、19、20 | H7: =SUMIFS(题目明细!$T:$T,题目明细!$A:$A,A7,题目明细!$G:$G,C7) | I7: =SUMIFS(题目明细!$S:$S,题目明细!$A:$A,A7,题目明细!$G:$G,C7)
A8: 2 | B8: MBTI维度细分（I/E、S/N、T/F、J/P） | C8: D3 | D8: 判断与计划 | E8: 决策时偏逻辑还是共情、执行偏弹性还是计划，高分偏共情与计划。 | F8: =COUNTIFS(题目明细!$A:$A,A8,题目明细!$G:$G,C8) | G8: 21、22、23、24、25、26、27、28、29、30 | H8: =SUMIFS(题目明细!$T:$T,题目明细!$A:$A,A8,题目明细!$G:$G,C8) | I8: =SUMIFS(题目明细!$S:$S,题目明细!$A:$A,A8,题目明细!$G:$G,C8)
A9: 3 | B9: 大五人格（Big Five） | C9: D1 | D9: 经验开放 | E9: 对新观念、新体验与抽象事物的兴趣和接纳度。 | F9: =COUNTIFS(题目明细!$A:$A,A9,题目明细!$G:$G,C9) | G9: 1、2、3、4、5、6、7、8、9、10、11、12、13、14、15 | H9: =SUMIFS(题目明细!$T:$T,题目明细!$A:$A,A9,题目明细!$G:$G,C9) | I9: =SUMIFS(题目明细!$S:$S,题目明细!$A:$A,A9,题目明细!$G:$G,C9)
A10: 3 | B10: 大五人格（Big Five） | C10: D2 | D10: 自律尽责 | E10: 目标感、条理性与对承诺和细节的把控程度。 | F10: =COUNTIFS(题目明细!$A:$A,A10,题目明细!$G:$G,C10) | G10: 16、17、18、19、20、21、22、23、24、25、26、27、28、29、30 | H10: =SUMIFS(题目明细!$T:$T,题目明细!$A:$A,A10,题目明细!$G:$G,C10) | I10: =SUMIFS(题目明细!$S:$S,题目明细!$A:$A,A10,题目明细!$G:$G,C10)
A11: 3 | B11: 大五人格（Big Five） | C11: D3 | D11: 人际温度 | E11: 与人相处时的热情、体贴与合作倾向。 | F11: =COUNTIFS(题目明细!$A:$A,A11,题目明细!$G:$G,C11) | G11: 31、32、33、34、35、36、37、38、39、40、41、42、43、44、45 | H11: =SUMIFS(题目明细!$T:$T,题目明细!$A:$A,A11,题目明细!$G:$G,C11) | I11: =SUMIFS(题目明细!$S:$S,题目明细!$A:$A,A11,题目明细!$G:$G,C11)
A12: 3 | B12: 大五人格（Big Five） | C12: D4 | D12: 情绪稳定 | E12: 面对压力与突发状况时的情绪波动与恢复力。 | F12: =COUNTIFS(题目明细!$A:$A,A12,题目明细!$G:$G,C12) | G12: 46、47、48、49、50、51、52、53、54、55、56、57、58、59、60 | H12: =SUMIFS(题目明细!$T:$T,题目明细!$A:$A,A12,题目明细!$G:$G,C12) | I12: =SUMIFS(题目明细!$S:$S,题目明细!$A:$A,A12,题目明细!$G:$G,C12)
A13: 4 | B13: 九型人格 | C13: D1 | D13: 原则与责任 | E13: 对标准、规则与正确性的坚持程度，高分偏完美倾向。 | F13: =COUNTIFS(题目明细!$A:$A,A13,题目明细!$G:$G,C13) | G13: 1、2、3、4、5、6、7、8、9、10、11、12、13、14、15 | H13: =SUMIFS(题目明细!$T:$T,题目明细!$A:$A,A13,题目明细!$G:$G,C13) | I13: =SUMIFS(题目明细!$S:$S,题目明细!$A:$A,A13,题目明细!$G:$G,C13)
... A1187: 391 | B1187: 日常物品选择投射 | C1187: D3 | D1187: 选择风格 | E1187: 物品与金钱决策中体现的自主性与消费理性 | F1187: =COUNTIFS(题目明细!$A:$A,A1187,题目明细!$G:$G,C1187) | G1187: 15、16、17、18、19、20、21 | H1187: =SUMIFS(题目明细!$T:$T,题目明细!$A:$A,A1187,题目明细!$G:$G,C1187) | I1187: =SUMIFS(题目明细!$S:$S,题目明细!$A:$A,A1187,题目明细!$G:$G,C1187)

Sheet 分数段分析
A1: 主题序号 | B1: 测评主题 | C1: 维度代码 | D1: 维度名称 | E1: 分数段 | F1: 下限 | G1: 上限 | H1: 评级 | I1: 分析 | J1: 建议
A2: 1 | B2: MBTI 16型人格 | C2: D1 | D2: 能量取向 | E2: 第1段 | F2: 20 | G2: 41 | H2: 低位 | I2: 内向倾向明显，独处时精力最充沛，热闹场合后需要独处回血，在少数深度关系里更自在。 | J2: 不必强迫自己合群，把社交按重要程度分配额度，优先维护少数高质量关系，活动后预留恢复时间。
A3: 1 | B3: MBTI 16型人格 | C3: D1 | D3: 能量取向 | E3: 第2段 | F3: 42 | G3: 63 | H3: 中位 | I3: 处于中间偏灵活的位置，独处与社交都能适应，但长时间偏向任何一侧都会感到疲惫或乏味。 | J3: 觉察每周的能量消耗节奏，交替安排独处充电与轻量社交，给两种模式都留出固定空间。定期做一次小复盘，微调节奏就能持续精进。
A4: 1 | B4: MBTI 16型人格 | C4: D1 | D4: 能量取向 | E4: 第3段 | F4: 64 | G4: 89 | H4: 高位 | I4: 外向倾向明显，与人互动让你充满电，主动健谈，人群中常是活跃与连接的担当。这一特质常是你的核心竞争力，值得有意识地经营与发挥。 | J4: 发挥连接者优势，多承担组织与协作角色，同时练习安静倾听，避免热情淹没他人的表达空间。
A5: 1 | B5: MBTI 16型人格 | C5: D2 | D5: 信息获取 | E5: 第1段 | F5: 20 | G5: 41 | H5: 低位 | I5: 偏实感风格，关注事实、细节与当下经验，讲究可验证可落地，观察力和执行力比较扎实。 | J5: 踏实是你的优势，遇到抽象议题时先追问它想解决什么问题，再落回具体步骤，逐步适应概念思维。
A6: 1 | B6: MBTI 16型人格 | C6: D2 | D6: 信息获取 | E6: 第2段 | F6: 42 | G6: 63 | H6: 中位 | I6: 能在细节与全局之间切换，既关注实际情况也乐于联想，理解抽象概念不算费力。多数场景下你应对得当，出现的波动基本属于正常范围。 | J6: 用一栏事实清单加一栏愿景设想的笔记方式，让两种思维各司其职，互补短板。定期做一次小复盘，微调节奏就能持续精进。
A7: 1 | B7: MBTI 16型人格 | C7: D2 | D7: 信息获取 | E7: 第3段 | F7: 64 | G7: 89 | H7: 高位 | I7: 偏直觉风格，联想快、点子多，容易被新的可能性吸引，对比喻、趋势和未来图景敏感。这一特质常是你的核心竞争力，值得有意识地经营与发挥。 | J7: 把灵感及时转成步骤与时间点，定期向注重细节的伙伴求证，防止好想法悬在空中落不了地。
A8: 1 | B8: MBTI 16型人格 | C8: D3 | D8: 决策方式 | E8: 第1段 | F8: 20 | G8: 41 | H8: 低位 | I8: 偏思考风格，决策讲逻辑、重标准，对事不对人，能在压力下保持客观和一致的判断。这种状态很常见，通常只反映当下的默认模式，并非固定不变的特质。 | J8: 传达结论时先接住对方处境再摆逻辑，在重要关系里练习先回应感受，再给出方案。从最小的行动开始，坚持两三周并用记录看见变化。
A9: 1 | B9: MBTI 16型人格 | C9: D3 | D9: 决策方式 | E9: 第2段 | F9: 42 | G9: 63 | H9: 中位 | I9: 决策时既讲道理也顾人情，能依据场合在客观分析与人际考量之间来回权衡。多数场景下你应对得当，出现的波动基本属于正常范围。 | J9: 事务性决定多用理性框架，涉及他人情绪的重大事项时，多问一句你希望我怎么帮你。定期做一次小复盘，微调节奏就能持续精进。
A10: 1 | B10: MBTI 16型人格 | C10: D3 | D10: 决策方式 | E10: 第3段 | F10: 64 | G10: 89 | H10: 高位 | I10: 偏情感风格，重视和谐与他人感受，同理心强，决策时常把人的因素放在事情前面。这一特质常是你的核心竞争力，值得有意识地经营与发挥。 | J10: 练习用数据和标准支撑善意决策，对不合理请求明确说不，避免过度共情造成自我消耗。记得定期自我复盘，防止优势在惯性里变成盲区。
A11: 1 | B11: MBTI 16型人格 | C11: D4 | D11: 生活态度 | E11: 第1段 | F11: 20 | G11: 41 | H11: 低位 | I11: 偏知觉风格，喜欢保留选择权，随遇而安，临场应变快，容易被死板的流程和承诺束缚。这种状态很常见，通常只反映当下的默认模式，并非固定不变的特质。 | J11: 只给关键事项设硬性节点，其余保留弹性，用提醒工具兜底，避免遗漏重要承诺。从最小的行动开始，坚持两三周并用记录看见变化。
A12: 1 | B12: MBTI 16型人格 | C12: D4 | D12: 生活态度 | E12: 第2段 | F12: 42 | G12: 63 | H12: 中位 | I12: 张弛有度，既能提前规划也能接受变化，多数时候在秩序与灵活之间自然调节。多数场景下你应对得当，出现的波动基本属于正常范围。 | J12: 把事项分成必须准时和可以随缘两档管理，让计划为生活服务，而不是被计划牵着走。定期做一次小复盘，微调节奏就能持续精进。
A13: 1 | B13: MBTI 16型人格 | C13: D4 | D13: 生活态度 | E13: 第3段 | F13: 64 | G13: 89 | H13: 高位 | I13: 偏判断风格，喜欢清单、日程与确定性，做事有头有尾，未完成事项容易一直挂在心上。这一特质常是你的核心竞争力，值得有意识地经营与发挥。 | J13: 给计划留出缓冲带，每周留一段无安排时间，在小事上练习即兴，降低对突变的应激反应。
... A3690: 391 | B3690: 日常物品选择投射 | C3690: D3 | D3690: 选择风格 | E3690: 第3段 | F3690: 22 | G3690: 29 | H3690: 高位 | I3690: 你的选择清晰自主，买与不买都出于真实需要，与物品的关系松弛清明，界限分明，互不绑架。 | J3690: 保持这份难得的清明，也可以帮家人朋友把关大件消费，让经验产生更大的价值，人见人夸。
