Workbook

Sheet 说明
A1: 学习力测评主题（20个侧面） · 题目与维度设计总表
A3: 覆盖范围：20 个互不重复的学习力主题，共 600 道原创题目（每主题 30 题）
A4: 生成时间：2026-10-01；题目为原创设计，未抄录任何真实量表原文
A6: 工作表结构：
A7: ① 学习力主题清单：20 个主题的设计说明（主题定位、考察维度预告）
A8: ② 主题总览：每主题一行，题数/维度数/分数段数由公式自动统计
A9: ③ 题目明细：每道题一行，含题干、题型、所属维度、各选项文本与分值
A10: ④ 维度设置：每个维度一行，含说明、包含题号、最低分/总分（公式汇总）
A11: ⑤ 分数段分析：每个维度 3-4 个分数段，含评级、分析解读与建议
A13: 计分口径（与前一份《psyctest_测评题目与维度.xlsx》完全一致）：
A14: · 单选题：得分为所选选项分值。情景选择类 4-5 个选项分值为 1..n 的排列；
A15: · 频率自评类：选项固定 从不/偶尔/经常/总是（1-4 分），反向陈述题分值 4/3/2/1；
... A24: 使用提示：学习韧性、考前焦虑等主题的分析与建议为非诊断表述，仅供自我探索与工具设计参考。

Sheet 学习力主题清单
A1: 序号 | B1: 主题 | C1: 出题风格 | D1: 题数 | E1: 主题定位与考察维度 | F1: 维度构成
A2: 1 | B2: 学习动机与兴趣 | C2: 频率自评 | D2: 30 | E2: 测内驱兴趣、价值认同、好奇探索、外部动机依赖四个维度，识别学习动力来源结构 | F2: 内在兴趣(D1)、价值认同(D2)、好奇探索(D3)、动机自主性(D4)
A3: 2 | B3: 学习自我效能感 | C3: 频率自评 | D3: 30 | E3: 测能力自信、任务发起、困难坚持、自我怀疑反向四个维度，评估"我能学会"的信念强度 | F3: 能力自信(D1)、任务发起(D2)、困难坚持(D3)、自信稳定性(D4)
A4: 3 | B4: 学习目标与计划管理 | C4: 情景选择 | D4: 30 | E4: 测目标设定质量、计划分解执行、复盘调整三个维度，评估把意图转化为行动的能力 | F4: 目标设定质量(D1)、计划分解执行(D2)、复盘调整(D3)
A5: 4 | B5: 时间管理与专注力 | C5: 频率自评 | D5: 30 | E5: 测时间规划、深度专注、抗干扰、疲劳恢复四个维度，评估单位时间学习密度 | F5: 时间规划(D1)、深度专注(D2)、抗干扰(D3)、疲劳恢复(D4)
A6: 5 | B6: 学习拖延与自律 | C6: 情景选择 | D6: 30 | E6: 测拖延启动、诱惑抵抗、情绪化回避、自我约束四个维度，识别拖延的类型与根源 | F6: 启动难易(D1)、诱惑抵抗(D2)、情绪化回避(D3)、自我约束力(D4)
A7: 6 | B7: 元认知与学习策略 | C7: 情景选择 | D7: 30 | E7: 测计划预演、过程监控、理解自检、策略调整四个维度，评估"关于学习的学习"能力 | F7: 计划预演(D1)、过程监控(D2)、理解自检(D3)、策略调整(D4)
A8: 7 | B8: 深度学习方式 | C8: 情景选择 | D8: 30 | E8: 测意义建构、主动关联、批判加工、应用导向四个维度，区分深层加工与浅层死记 | F8: 意义建构(D1)、主动关联(D2)、批判加工(D3)、应用导向(D4)
A9: 8 | B9: 记忆力与知识巩固 | C9: 频率自评 | D9: 30 | E9: 测编码策略、间隔复习、提取练习、遗忘焦虑四个维度，评估记忆科学的使用水平 | F9: 编码策略(D1)、间隔复习(D2)、提取练习(D3)、遗忘焦虑(D4)
A10: 9 | B10: 逻辑推理与思维敏捷 | C10: 知识问答 | D10: 30 | E10: 测数字推理、语言逻辑、图形规律、因果论证四个维度，答对计分，题目须有唯一正确答案 | F10: 数字推理(D1)、语言逻辑(D2)、图形规律(D3)、因果论证(D4)
A11: 10 | B11: 批判性思维与独立思考 | C11: 情景选择 | D11: 30 | E11: 测证据意识、假设质疑、观点甄别、独立判断四个维度，评估不盲从的思考习惯 | F11: 证据意识(D1)、假设质疑(D2)、观点甄别(D3)、独立判断(D4)
A12: 11 | B12: 创造力与发散思维 | C12: 情景选择 | D12: 30 | E12: 测流畅联想、灵活变通、独创想法、好奇冒险四个维度，评估产生新想法的能力倾向 | F12: 流畅联想(D1)、灵活变通(D2)、独创想法(D3)、好奇冒险(D4)
A13: 12 | B13: 阅读理解与信息提取 | C13: 频率自评 | D13: 30 | E13: 测整体把握、关键捕捉、结构梳理、推断深化四个维度，评估从文本中获取意义的效率 | F13: 整体把握(D1)、关键捕捉(D2)、结构梳理(D3)、推断深化(D4)
... A21: 20 | B21: 学习反馈与错题管理 | C21: 情景选择 | D21: 30 | E21: 测主动求反馈、错题归因、订正迭代、考后复盘四个维度，评估利用反馈改进的能力 | F21: 主动求反馈(D1)、错题归因(D2)、订正迭代(D3)、考后复盘(D4)

Sheet 主题总览
A1: 主题序号 | B1: 一级主题域 | C1: 测评主题 | D1: 出题风格 | E1: 题数 | F1: 维度数 | G1: 分数段数
A2: 1 | B2: 学习力 | C2: 学习动机与兴趣 | D2: 频率自评 | E2: =COUNTIF(题目明细!$A:$A,A2) | F2: =COUNTIF(维度设置!$A:$A,A2) | G2: =COUNTIF(分数段分析!$A:$A,A2)
A3: 2 | B3: 学习力 | C3: 学习自我效能感 | D3: 频率自评 | E3: =COUNTIF(题目明细!$A:$A,A3) | F3: =COUNTIF(维度设置!$A:$A,A3) | G3: =COUNTIF(分数段分析!$A:$A,A3)
A4: 3 | B4: 学习力 | C4: 学习目标与计划管理 | D4: 情景选择 | E4: =COUNTIF(题目明细!$A:$A,A4) | F4: =COUNTIF(维度设置!$A:$A,A4) | G4: =COUNTIF(分数段分析!$A:$A,A4)
A5: 4 | B5: 学习力 | C5: 时间管理与专注力 | D5: 频率自评 | E5: =COUNTIF(题目明细!$A:$A,A5) | F5: =COUNTIF(维度设置!$A:$A,A5) | G5: =COUNTIF(分数段分析!$A:$A,A5)
A6: 5 | B6: 学习力 | C6: 学习拖延与自律 | D6: 情景选择 | E6: =COUNTIF(题目明细!$A:$A,A6) | F6: =COUNTIF(维度设置!$A:$A,A6) | G6: =COUNTIF(分数段分析!$A:$A,A6)
A7: 6 | B7: 学习力 | C7: 元认知与学习策略 | D7: 情景选择 | E7: =COUNTIF(题目明细!$A:$A,A7) | F7: =COUNTIF(维度设置!$A:$A,A7) | G7: =COUNTIF(分数段分析!$A:$A,A7)
A8: 7 | B8: 学习力 | C8: 深度学习方式 | D8: 情景选择 | E8: =COUNTIF(题目明细!$A:$A,A8) | F8: =COUNTIF(维度设置!$A:$A,A8) | G8: =COUNTIF(分数段分析!$A:$A,A8)
A9: 8 | B9: 学习力 | C9: 记忆力与知识巩固 | D9: 频率自评 | E9: =COUNTIF(题目明细!$A:$A,A9) | F9: =COUNTIF(维度设置!$A:$A,A9) | G9: =COUNTIF(分数段分析!$A:$A,A9)
A10: 9 | B10: 学习力 | C10: 逻辑推理与思维敏捷 | D10: 知识问答 | E10: =COUNTIF(题目明细!$A:$A,A10) | F10: =COUNTIF(维度设置!$A:$A,A10) | G10: =COUNTIF(分数段分析!$A:$A,A10)
A11: 10 | B11: 学习力 | C11: 批判性思维与独立思考 | D11: 情景选择 | E11: =COUNTIF(题目明细!$A:$A,A11) | F11: =COUNTIF(维度设置!$A:$A,A11) | G11: =COUNTIF(分数段分析!$A:$A,A11)
A12: 11 | B12: 学习力 | C12: 创造力与发散思维 | D12: 情景选择 | E12: =COUNTIF(题目明细!$A:$A,A12) | F12: =COUNTIF(维度设置!$A:$A,A12) | G12: =COUNTIF(分数段分析!$A:$A,A12)
A13: 12 | B13: 学习力 | C13: 阅读理解与信息提取 | D13: 频率自评 | E13: =COUNTIF(题目明细!$A:$A,A13) | F13: =COUNTIF(维度设置!$A:$A,A13) | G13: =COUNTIF(分数段分析!$A:$A,A13)
... A21: 20 | B21: 学习力 | C21: 学习反馈与错题管理 | D21: 情景选择 | E21: =COUNTIF(题目明细!$A:$A,A21) | F21: =COUNTIF(维度设置!$A:$A,A21) | G21: =COUNTIF(分数段分析!$A:$A,A21)

Sheet 题目明细
A1: 主题序号 | B1: 一级主题域 | C1: 测评主题 | D1: 题号 | E1: 题干 | F1: 题型 | G1: 维度代码 | H1: 维度名称 | I1: 选项A文本 | J1: A分值 | K1: 选项B文本 | L1: B分值 | M1: 选项C文本 | N1: C分值 | O1: 选项D文本 | P1: D分值 | Q1: 选项E文本 | R1: E分值 | S1: 题目满分 | T1: 题目最低分
A2: 1 | B2: 学习力 | C2: 学习动机与兴趣 | D2: 1 | E2: 我在钻研自己感兴趣的内容时感到由衷的愉快。 | F2: 单选 | G2: D1 | H2: 内在兴趣 | I2: 从不 | J2: 1 | K2: 偶尔 | L2: 2 | M2: 经常 | N2: 3 | O2: 总是 | P2: 4 | S2: =MAX(J2,L2,N2,P2) | T2: =MIN(J2,L2,N2,P2)
A3: 1 | B3: 学习力 | C3: 学习动机与兴趣 | D3: 2 | E3: 我面对有些枯燥的科目时，也能找到有趣的切入点。 | F3: 单选 | G3: D1 | H3: 内在兴趣 | I3: 从不 | J3: 1 | K3: 偶尔 | L3: 2 | M3: 经常 | N3: 3 | O3: 总是 | P3: 4 | S3: =MAX(J3,L3,N3,P3) | T3: =MIN(J3,L3,N3,P3)
A4: 1 | B4: 学习力 | C4: 学习动机与兴趣 | D4: 3 | E4: 我在没有兴趣支撑时，几乎无法逼自己打开书本。 | F4: 单选 | G4: D1 | H4: 内在兴趣 | I4: 从不 | J4: 4 | K4: 偶尔 | L4: 3 | M4: 经常 | N4: 2 | O4: 总是 | P4: 1 | S4: =MAX(J4,L4,N4,P4) | T4: =MIN(J4,L4,N4,P4)
A5: 1 | B5: 学习力 | C5: 学习动机与兴趣 | D5: 4 | E5: 我学习时更享受弄懂问题本身的快乐，而非只看分数。 | F5: 单选 | G5: D1 | H5: 内在兴趣 | I5: 从不 | J5: 1 | K5: 偶尔 | L5: 2 | M5: 经常 | N5: 3 | O5: 总是 | P5: 4 | S5: =MAX(J5,L5,N5,P5) | T5: =MIN(J5,L5,N5,P5)
A6: 1 | B6: 学习力 | C6: 学习动机与兴趣 | D6: 5 | E6: 我在学喜欢的内容时，常常忘记时间的流逝。 | F6: 单选 | G6: D1 | H6: 内在兴趣 | I6: 从不 | J6: 1 | K6: 偶尔 | L6: 2 | M6: 经常 | N6: 3 | O6: 总是 | P6: 4 | S6: =MAX(J6,L6,N6,P6) | T6: =MIN(J6,L6,N6,P6)
A7: 1 | B7: 学习力 | C7: 学习动机与兴趣 | D7: 6 | E7: 我觉得学习只是熬任务，尝不到什么乐趣。 | F7: 单选 | G7: D1 | H7: 内在兴趣 | I7: 从不 | J7: 4 | K7: 偶尔 | L7: 3 | M7: 经常 | N7: 2 | O7: 总是 | P7: 1 | S7: =MAX(J7,L7,N7,P7) | T7: =MIN(J7,L7,N7,P7)
A8: 1 | B8: 学习力 | C8: 学习动机与兴趣 | D8: 7 | E8: 我会主动想办法，把感兴趣的内容学得更深入一些。 | F8: 单选 | G8: D1 | H8: 内在兴趣 | I8: 从不 | J8: 1 | K8: 偶尔 | L8: 2 | M8: 经常 | N8: 3 | O8: 总是 | P8: 4 | S8: =MAX(J8,L8,N8,P8) | T8: =MIN(J8,L8,N8,P8)
A9: 1 | B9: 学习力 | C9: 学习动机与兴趣 | D9: 8 | E9: 我就算没有任何考试，也愿意继续学自己喜欢的东西。 | F9: 单选 | G9: D1 | H9: 内在兴趣 | I9: 从不 | J9: 1 | K9: 偶尔 | L9: 2 | M9: 经常 | N9: 3 | O9: 总是 | P9: 4 | S9: =MAX(J9,L9,N9,P9) | T9: =MIN(J9,L9,N9,P9)
A10: 1 | B10: 学习力 | C10: 学习动机与兴趣 | D10: 9 | E10: 我能说出当前学习对我未来至少两点具体意义。 | F10: 单选 | G10: D2 | H10: 价值认同 | I10: 从不 | J10: 1 | K10: 偶尔 | L10: 2 | M10: 经常 | N10: 3 | O10: 总是 | P10: 4 | S10: =MAX(J10,L10,N10,P10) | T10: =MIN(J10,L10,N10,P10)
A11: 1 | B11: 学习力 | C11: 学习动机与兴趣 | D11: 10 | E11: 我在觉得学习没意思时，会提醒自己长远的目标。 | F11: 单选 | G11: D2 | H11: 价值认同 | I11: 从不 | J11: 1 | K11: 偶尔 | L11: 2 | M11: 经常 | N11: 3 | O11: 总是 | P11: 4 | S11: =MAX(J11,L11,N11,P11) | T11: =MIN(J11,L11,N11,P11)
A12: 1 | B12: 学习力 | C12: 学习动机与兴趣 | D12: 11 | E12: 我经常觉得现在学的东西将来完全用不上。 | F12: 单选 | G12: D2 | H12: 价值认同 | I12: 从不 | J12: 4 | K12: 偶尔 | L12: 3 | M12: 经常 | N12: 2 | O12: 总是 | P12: 1 | S12: =MAX(J12,L12,N12,P12) | T12: =MIN(J12,L12,N12,P12)
A13: 1 | B13: 学习力 | C13: 学习动机与兴趣 | D13: 12 | E13: 我会把困难的科目和自己真正在乎的目标联系起来学。 | F13: 单选 | G13: D2 | H13: 价值认同 | I13: 从不 | J13: 1 | K13: 偶尔 | L13: 2 | M13: 经常 | N13: 3 | O13: 总是 | P13: 4 | S13: =MAX(J13,L13,N13,P13) | T13: =MIN(J13,L13,N13,P13)
... A601: 20 | B601: 学习力 | C601: 学习反馈与错题管理 | D601: 30 | E601: 以下哪些是你考后复盘时会做的事（多选） | F601: 多选 | G601: D4 | H601: 考后复盘 | I601: 按题型统计正确率找薄弱点 | J601: 2 | K601: 写一条下次考试的具体改进点 | L601: 1 | M601: 看完分数就收起来不分析 | N601: 0 | O601: 记录考场状态和时间分配 | P601: 2 | S601: =MAX(J601,L601,N601,P601) | T601: =MIN(J601,L601,N601,P601)

Sheet 维度设置
A1: 主题序号 | B1: 测评主题 | C1: 维度代码 | D1: 维度名称 | E1: 维度说明 | F1: 题目数 | G1: 包含题号 | H1: 维度最低分 | I1: 维度总分
A2: 1 | B2: 学习动机与兴趣 | C2: D1 | D2: 内在兴趣 | E2: 学习在多大程度上被内容本身的趣味与快乐吸引 | F2: =COUNTIFS(题目明细!$A:$A,A2,题目明细!$G:$G,C2) | G2: 1、2、3、4、5、6、7、8 | H2: =SUMIFS(题目明细!$T:$T,题目明细!$A:$A,A2,题目明细!$G:$G,C2) | I2: =SUMIFS(题目明细!$S:$S,题目明细!$A:$A,A2,题目明细!$G:$G,C2)
A3: 1 | B3: 学习动机与兴趣 | C3: D2 | D3: 价值认同 | E3: 对所学知识的作用与长远意义的认可程度 | F3: =COUNTIFS(题目明细!$A:$A,A3,题目明细!$G:$G,C3) | G3: 9、10、11、12、13、14、15 | H3: =SUMIFS(题目明细!$T:$T,题目明细!$A:$A,A3,题目明细!$G:$G,C3) | I3: =SUMIFS(题目明细!$S:$S,题目明细!$A:$A,A3,题目明细!$G:$G,C3)
A4: 1 | B4: 学习动机与兴趣 | C4: D3 | D4: 好奇探索 | E4: 出于好奇而主动超出任务范围探究新知的倾向 | F4: =COUNTIFS(题目明细!$A:$A,A4,题目明细!$G:$G,C4) | G4: 16、17、18、19、20、21、22、23 | H4: =SUMIFS(题目明细!$T:$T,题目明细!$A:$A,A4,题目明细!$G:$G,C4) | I4: =SUMIFS(题目明细!$S:$S,题目明细!$A:$A,A4,题目明细!$G:$G,C4)
A5: 1 | B5: 学习动机与兴趣 | C5: D4 | D5: 动机自主性 | E5: 动力源自内部而非依赖外部监督与奖惩的程度 | F5: =COUNTIFS(题目明细!$A:$A,A5,题目明细!$G:$G,C5) | G5: 24、25、26、27、28、29、30 | H5: =SUMIFS(题目明细!$T:$T,题目明细!$A:$A,A5,题目明细!$G:$G,C5) | I5: =SUMIFS(题目明细!$S:$S,题目明细!$A:$A,A5,题目明细!$G:$G,C5)
A6: 2 | B6: 学习自我效能感 | C6: D1 | D6: 能力自信 | E6: 对自身学习能力的信任程度，相信自己学得会 | F6: =COUNTIFS(题目明细!$A:$A,A6,题目明细!$G:$G,C6) | G6: 1、2、3、4、5、6、7 | H6: =SUMIFS(题目明细!$T:$T,题目明细!$A:$A,A6,题目明细!$G:$G,C6) | I6: =SUMIFS(题目明细!$S:$S,题目明细!$A:$A,A6,题目明细!$G:$G,C6)
A7: 2 | B7: 学习自我效能感 | C7: D2 | D7: 任务发起 | E7: 主动启动学习任务时表现出的果断与自信 | F7: =COUNTIFS(题目明细!$A:$A,A7,题目明细!$G:$G,C7) | G7: 8、9、10、11、12、13、14、15 | H7: =SUMIFS(题目明细!$T:$T,题目明细!$A:$A,A7,题目明细!$G:$G,C7) | I7: =SUMIFS(题目明细!$S:$S,题目明细!$A:$A,A7,题目明细!$G:$G,C7)
A8: 2 | B8: 学习自我效能感 | C8: D3 | D8: 困难坚持 | E8: 遇到阻碍与挫折后维持努力不回退的程度 | F8: =COUNTIFS(题目明细!$A:$A,A8,题目明细!$G:$G,C8) | G8: 16、17、18、19、20、21、22、23 | H8: =SUMIFS(题目明细!$T:$T,题目明细!$A:$A,A8,题目明细!$G:$G,C8) | I8: =SUMIFS(题目明细!$S:$S,题目明细!$A:$A,A8,题目明细!$G:$G,C8)
A9: 2 | B9: 学习自我效能感 | C9: D4 | D9: 自信稳定性 | E9: 自我评价稳定，不易因成败陷入自我怀疑 | F9: =COUNTIFS(题目明细!$A:$A,A9,题目明细!$G:$G,C9) | G9: 24、25、26、27、28、29、30 | H9: =SUMIFS(题目明细!$T:$T,题目明细!$A:$A,A9,题目明细!$G:$G,C9) | I9: =SUMIFS(题目明细!$S:$S,题目明细!$A:$A,A9,题目明细!$G:$G,C9)
A10: 3 | B10: 学习目标与计划管理 | C10: D1 | D10: 目标设定质量 | E10: 目标是否具体可测、难度适中且认同价值 | F10: =COUNTIFS(题目明细!$A:$A,A10,题目明细!$G:$G,C10) | G10: 1、2、3、4、5、6、7、8、9、10 | H10: =SUMIFS(题目明细!$T:$T,题目明细!$A:$A,A10,题目明细!$G:$G,C10) | I10: =SUMIFS(题目明细!$S:$S,题目明细!$A:$A,A10,题目明细!$G:$G,C10)
A11: 3 | B11: 学习目标与计划管理 | C11: D2 | D11: 计划分解执行 | E11: 把目标拆成每日行动并落实的程度 | F11: =COUNTIFS(题目明细!$A:$A,A11,题目明细!$G:$G,C11) | G11: 11、12、13、14、15、16、17、18、19、20 | H11: =SUMIFS(题目明细!$T:$T,题目明细!$A:$A,A11,题目明细!$G:$G,C11) | I11: =SUMIFS(题目明细!$S:$S,题目明细!$A:$A,A11,题目明细!$G:$G,C11)
A12: 3 | B12: 学习目标与计划管理 | C12: D3 | D12: 复盘调整 | E12: 回顾学习效果并修正目标与行动的程度 | F12: =COUNTIFS(题目明细!$A:$A,A12,题目明细!$G:$G,C12) | G12: 21、22、23、24、25、26、27、28、29、30 | H12: =SUMIFS(题目明细!$T:$T,题目明细!$A:$A,A12,题目明细!$G:$G,C12) | I12: =SUMIFS(题目明细!$S:$S,题目明细!$A:$A,A12,题目明细!$G:$G,C12)
A13: 4 | B13: 时间管理与专注力 | C13: D1 | D13: 时间规划 | E13: 学习时间是否提前安排并得到落实 | F13: =COUNTIFS(题目明细!$A:$A,A13,题目明细!$G:$G,C13) | G13: 1、2、3、4、5、6、7 | H13: =SUMIFS(题目明细!$T:$T,题目明细!$A:$A,A13,题目明细!$G:$G,C13) | I13: =SUMIFS(题目明细!$S:$S,题目明细!$A:$A,A13,题目明细!$G:$G,C13)
... A80: 20 | B80: 学习反馈与错题管理 | C80: D4 | D80: 考后复盘 | E80: 考试结束后系统分析得失并转化为行动的习惯 | F80: =COUNTIFS(题目明细!$A:$A,A80,题目明细!$G:$G,C80) | G80: 23、24、25、26、27、28、29、30 | H80: =SUMIFS(题目明细!$T:$T,题目明细!$A:$A,A80,题目明细!$G:$G,C80) | I80: =SUMIFS(题目明细!$S:$S,题目明细!$A:$A,A80,题目明细!$G:$G,C80)

Sheet 分数段分析
A1: 主题序号 | B1: 测评主题 | C1: 维度代码 | D1: 维度名称 | E1: 分数段 | F1: 下限 | G1: 上限 | H1: 评级 | I1: 分析 | J1: 建议
A2: 1 | B2: 学习动机与兴趣 | C2: D1 | D2: 内在兴趣 | E2: 第1段 | F2: 8 | G2: 14 | H2: 低位 | I2: 学习主要靠外部要求推动，很难从内容本身尝到乐趣，长期下来容易疲惫抵触，投入需要消耗大量意志力。 | J2: 从感兴趣的小切口入手，每天留十五分钟学自己选的内容，先积累与书本相处的愉悦感，再谈深度。
A3: 1 | B3: 学习动机与兴趣 | C3: D1 | D3: 内在兴趣 | E3: 第2段 | F3: 15 | G3: 22 | H3: 中位 | I3: 对部分科目有真实兴趣，但兴趣容易被考试压力和作业量冲淡，乐趣忽高忽低，状态随外部节奏摆动。 | J3: 每天记录一个学习中觉得有意思的瞬间，周末给自己安排一段自由钻研时间，主动保护兴趣火苗。
A4: 1 | B4: 学习动机与兴趣 | C4: D1 | D4: 内在兴趣 | E4: 第3段 | F4: 23 | G4: 32 | H4: 高位 | I4: 兴趣是学习的主要引擎之一，钻研过程本身就能带来满足，即使没有外部奖励也愿意投入，状态较为稳定。 | J4: 用兴趣做线索带动应试科目，例如把喜欢的领域与学科知识挂钩，同时设定边界，避免过度沉迷课外内容。
A5: 1 | B5: 学习动机与兴趣 | C5: D2 | D5: 价值认同 | E5: 第1段 | F5: 7 | G5: 13 | H5: 低位 | I5: 经常怀疑所学无用，学习与个人未来之间缺少连接，动力浮在表面，一遇挫折就容易想放弃。 | J5: 写下学习曾带给你的三个具体好处，再选一个在意的目标，把当前科目拆出对它最直接的帮助逐条对照。
A6: 1 | B6: 学习动机与兴趣 | C6: D2 | D6: 价值认同 | E6: 第2段 | F6: 14 | G6: 20 | H6: 中位 | I6: 理智上认可学习的意义，但这份认同不够牢固，遇到难题或枯燥期时容易模糊，需要不断被提醒。 | J6: 把宏大的意义换算成每月可见的小目标，达成后回头确认它确实让自己靠近了想要的方向，强化实感。
A7: 1 | B7: 学习动机与兴趣 | C7: D2 | D7: 价值认同 | E7: 第3段 | F7: 21 | G7: 28 | H7: 高位 | I7: 对学习的价值有较坚定的认同，能用长远意义带动当下行动，熬过枯燥阶段的内在支撑比较充足。 | J7: 可以试着帮助身边觉得学习无用的同学梳理意义，讲述的过程也会进一步巩固你自己的信念。
A8: 1 | B8: 学习动机与兴趣 | C8: D3 | D8: 好奇探索 | E8: 第1段 | F8: 8 | G8: 14 | H8: 低位 | I8: 学习基本止步于任务划定的范围，对未知缺少追问的冲动，获取知识的方式偏被动等待安排。 | J8: 从每天课上一个小白问题开始，用放学后十分钟查到底，先让追问的肌肉动起来，再逐步扩大探索半径。
A9: 1 | B9: 学习动机与兴趣 | C9: D3 | D9: 好奇探索 | E9: 第2段 | F9: 15 | G9: 22 | H9: 中位 | I9: 有一定好奇心，偶尔会想多了解一点，但缺少把好奇落实为查证和钻研的行动，探索常半途而废。 | J9: 建一个探索小本，每周记一个想弄明白的问题并安排固定时间研究，月末给自己一次完整的解答仪式。
A10: 1 | B10: 学习动机与兴趣 | C10: D3 | D10: 好奇探索 | E10: 第3段 | F10: 23 | G10: 32 | H10: 高位 | I10: 求知欲旺盛，喜欢追根究底和触类旁通，主动探索已经形成习惯，常常学到任务之外的东西。 | J10: 把发散的兴趣收拢成一两条主线，与课内体系互相印证，让课外探索反哺理解而不是挤占基础时间。
A11: 1 | B11: 学习动机与兴趣 | C11: D4 | D11: 动机自主性 | E11: 第1段 | F11: 7 | G11: 13 | H11: 低位 | I11: 动力高度依赖催促、监督和奖惩，外部压力一撤，学习就像断电一样停摆，自主推动的力量偏弱。 | J11: 用小清单代替他人催促：自己列任务、自己核对、完成后给自己记一笔成就，逐步把外部监督内化。
A12: 1 | B12: 学习动机与兴趣 | C12: D4 | D12: 动机自主性 | E12: 第2段 | F12: 14 | G12: 20 | H12: 中位 | I12: 多数时候能主动学习，但在缺乏外部压力的时段仍会松劲，恢复也慢，动力强弱明显随环境提醒摆动。 | J12: 自己定一份周计划并自己负责核对完成，晚上记录执行情况，逐步减少对他人的提醒依赖，让学习节奏回归自主。
A13: 1 | B13: 学习动机与兴趣 | C13: D4 | D13: 动机自主性 | E13: 第3段 | F13: 21 | G13: 28 | H13: 高位 | I13: 动力主要来自自身，学习节奏由内在标准决定，不因无人监督而松懈，也不因奖励诱惑而跑偏。 | J13: 保持自驱的同时预留外部反馈渠道，定期和老师同学对一对方向，避免独立运行变成闭门造车。
... A298: 20 | B298: 学习反馈与错题管理 | C298: D4 | D298: 考后复盘 | E298: 第4段 | F298: 27 | G298: 33 | H298: 高位 | I298: 你的考后复盘已经成为固定流程，能从每次考试里精准提取改进方向，并有效地落实到行动上。 | J298: 复盘能力很成熟，可以进一步加入策略层面的思考，不只是改正错题，更审视整体复习方法本身要不要升级。
